[{"confirmed":"600,108,679","daily_confirmed":"719,043","recovered":"0","daily_recovered":"0","deaths":"6,484,151","daily_deaths":"2,521","infected":"593,624,528","daily_infected":"716,522","vaccines":"12,551,707,254","daily_vaccines":"4,044,022","country":"World","iso":"WD","region":"WD","last_update":"2022-08-27 15:25:11"},{"confirmed":"94,171,060","daily_confirmed":"142,220","recovered":"0","daily_recovered":"0","deaths":"1,043,783","daily_deaths":"694","infected":"93,127,277","daily_infected":"141,526","vaccines":"608,937,334","daily_vaccines":"0","country":"US","iso":"US","region":"Americas","last_update":"2022-08-27 15:25:11"},{"confirmed":"44,398,696","daily_confirmed":"9,520","recovered":"0","daily_recovered":"0","deaths":"527,597","daily_deaths":"41","infected":"43,871,099","daily_infected":"9,479","vaccines":"2,111,876,002","daily_vaccines":"3,151,893","country":"India","iso":"IN","region":"Asia","last_update":"2022-08-27 15:25:11"},{"confirmed":"34,662,834","daily_confirmed":"18,116","recovered":"0","daily_recovered":"0","deaths":"154,897","daily_deaths":"51","infected":"34,507,937","daily_infected":"18,065","vaccines":"149,253,768","daily_vaccines":"0","country":"France","iso":"FR","region":"Europe","last_update":"2022-08-27 15:25:11"},{"confirmed":"34,368,909","daily_confirmed":"18,270","recovered":"0","daily_recovered":"0","deaths":"683,397","daily_deaths":"164","infected":"33,685,512","daily_infected":"18,106","vaccines":"468,802,225","daily_vaccines":"61,149","country":"Brazil","iso":"BR","region":"Americas","last_update":"2022-08-27 15:25:11"},{"confirmed":"32,041,348","daily_confirmed":"33,226","recovered":"0","daily_recovered":"0","deaths":"147,104","daily_deaths":"101","infected":"31,894,244","daily_infected":"33,125","vaccines":"184,604,363","daily_vaccines":"23,728","country":"Germany","iso":"DE","region":"Europe","last_update":"2022-08-27 15:25:11"},{"confirmed":"23,708,623","daily_confirmed":"157","recovered":"0","daily_recovered":"0","deaths":"205,414","daily_deaths":"1","infected":"23,503,209","daily_infected":"156","vaccines":"151,011,469","daily_vaccines":"0","country":"United Kingdom","iso":"GB","region":"Europe","last_update":"2022-08-27 15:25:11"},{"confirmed":"22,898,523","daily_confirmed":"95,538","recovered":"0","daily_recovered":"0","deaths":"26,499","daily_deaths":"86","infected":"22,872,024","daily_infected":"95,452","vaccines":"0","daily_vaccines":"0","country":"Korea, South","iso":"KR","region":"Asia","last_update":"2022-08-27 15:25:11"},{"confirmed":"21,767,060","daily_confirmed":"21,995","recovered":"0","daily_recovered":"0","deaths":"175,226","daily_deaths":"99","infected":"21,591,834","daily_infected":"21,896","vaccines":"140,279,364","daily_vaccines":"19,024","country":"Italy","iso":"IT","region":"Europe","last_update":"2022-08-27 15:25:11"},{"confirmed":"19,030,966","daily_confirmed":"45,792","recovered":"0","daily_recovered":"0","deaths":"376,131","daily_deaths":"79","infected":"18,654,835","daily_infected":"45,713","vaccines":"173,452,712","daily_vaccines":"4,120","country":"Russia","iso":"RU","region":"Europe","last_update":"2022-08-27 15:25:11"},{"confirmed":"18,194,170","daily_confirmed":"192,305","recovered":"0","daily_recovered":"0","deaths":"38,565","daily_deaths":"321","infected":"18,155,605","daily_infected":"191,984","vaccines":"311,980,293","daily_vaccines":"0","country":"Japan","iso":"JP","region":"Asia","last_update":"2022-08-27 15:25:11"},{"confirmed":"16,671,848","daily_confirmed":"0","recovered":"0","daily_recovered":"0","deaths":"100,400","daily_deaths":"0","infected":"16,571,448","daily_infected":"0","vaccines":"151,951,291","daily_vaccines":"26,369","country":"Turkey","iso":"TR","region":"Asia","last_update":"2022-08-27 15:25:11"},{"confirmed":"13,332,976","daily_confirmed":"9,192","recovered":"0","daily_recovered":"0","deaths":"112,454","daily_deaths":"208","infected":"13,220,522","daily_infected":"8,984","vaccines":"95,643,377","daily_vaccines":"0","country":"Spain","iso":"ES","region":"Europe","last_update":"2022-08-27 15:25:11"},{"confirmed":"11,399,400","daily_confirmed":"3,195","recovered":"0","daily_recovered":"0","deaths":"43,110","daily_deaths":"0","infected":"11,356,290","daily_infected":"3,195","vaccines":"253,398,589","daily_vaccines":"0","country":"Vietnam","iso":"VN","region":"Asia","last_update":"2022-08-27 15:25:11"},{"confirmed":"9,987,913","daily_confirmed":"11,177","recovered":"0","daily_recovered":"0","deaths":"13,734","daily_deaths":"87","infected":"9,974,179","daily_infected":"11,090","vaccines":"58,373,794","daily_vaccines":"0","country":"Australia","iso":"AU","region":"Oceania","last_update":"2022-08-27 15:25:11"},{"confirmed":"9,658,391","daily_confirmed":"0","recovered":"0","daily_recovered":"0","deaths":"129,646","daily_deaths":"0","infected":"9,528,745","daily_infected":"0","vaccines":"108,793,079","daily_vaccines":"7","country":"Argentina","iso":"AR","region":"Americas","last_update":"2022-08-27 15:25:11"},{"confirmed":"8,490,917","daily_confirmed":"1,154","recovered":"0","daily_recovered":"0","deaths":"23,232","daily_deaths":"2","infected":"8,467,685","daily_infected":"1,152","vaccines":"36,097,521","daily_vaccines":"0","country":"Netherlands","iso":"NL","region":"Europe","last_update":"2022-08-27 15:25:11"},{"confirmed":"7,520,993","daily_confirmed":"2,019","recovered":"0","daily_recovered":"0","deaths":"143,647","daily_deaths":"35","infected":"7,377,346","daily_infected":"1,984","vaccines":"150,984,487","daily_vaccines":"0","country":"Iran","iso":"IR","region":"Asia","last_update":"2022-08-27 15:25:11"},{"confirmed":"7,001,590","daily_confirmed":"0","recovered":"0","daily_recovered":"0","deaths":"329,289","daily_deaths":"0","infected":"6,672,301","daily_infected":"0","vaccines":"209,673,612","daily_vaccines":"0","country":"Mexico","iso":"MX","region":"Americas","last_update":"2022-08-27 15:25:11"},{"confirmed":"6,338,906","daily_confirmed":"4,549","recovered":"0","daily_recovered":"0","deaths":"157,478","daily_deaths":"21","infected":"6,181,428","daily_infected":"4,528","vaccines":"432,525,181","daily_vaccines":"0","country":"Indonesia","iso":"ID","region":"Asia","last_update":"2022-08-27 15:25:11"},{"confirmed":"6,299,595","daily_confirmed":"0","recovered":"0","daily_recovered":"0","deaths":"141,519","daily_deaths":"0","infected":"6,158,076","daily_infected":"0","vaccines":"87,566,541","daily_vaccines":"0","country":"Colombia","iso":"CO","region":"Americas","last_update":"2022-08-27 15:25:11"},{"confirmed":"6,162,667","daily_confirmed":"3,850","recovered":"0","daily_recovered":"0","deaths":"117,007","daily_deaths":"40","infected":"6,045,660","daily_infected":"3,810","vaccines":"56,059,371","daily_vaccines":"0","country":"Poland","iso":"PL","region":"Europe","last_update":"2022-08-27 15:25:11"},{"confirmed":"5,409,185","daily_confirmed":"3,090","recovered":"0","daily_recovered":"0","deaths":"24,813","daily_deaths":"3","infected":"5,384,372","daily_infected":"3,087","vaccines":"24,871,191","daily_vaccines":"0","country":"Portugal","iso":"PT","region":"Europe","last_update":"2022-08-27 15:25:11"},{"confirmed":"5,325,948","daily_confirmed":"660","recovered":"0","daily_recovered":"0","deaths":"116,582","daily_deaths":"2","infected":"5,209,366","daily_infected":"658","vaccines":"31,668,577","daily_vaccines":"0","country":"Ukraine","iso":"UA","region":"Europe","last_update":"2022-08-27 15:25:11"},{"confirmed":"5,168,997","daily_confirmed":"26,718","recovered":"0","daily_recovered":"0","deaths":"9,773","daily_deaths":"45","infected":"5,159,224","daily_infected":"26,673","vaccines":"0","daily_vaccines":"0","country":"Taiwan*","iso":"TW","region":"Asia","last_update":"2022-08-27 15:25:11"},{"confirmed":"4,934,634","daily_confirmed":"5,500","recovered":"0","daily_recovered":"0","deaths":"20,613","daily_deaths":"9","infected":"4,914,021","daily_infected":"5,491","vaccines":"19,030,820","daily_vaccines":"0","country":"Austria","iso":"AT","region":"Europe","last_update":"2022-08-27 15:25:11"},{"confirmed":"4,771,512","daily_confirmed":"3,118","recovered":"0","daily_recovered":"0","deaths":"36,191","daily_deaths":"6","infected":"4,735,321","daily_infected":"3,112","vaccines":"72,034,685","daily_vaccines":"5,908","country":"Malaysia","iso":"MY","region":"Asia","last_update":"2022-08-27 15:25:11"},{"confirmed":"4,712,025","daily_confirmed":"0","recovered":"0","daily_recovered":"0","deaths":"32,335","daily_deaths":"0","infected":"4,679,690","daily_infected":"0","vaccines":"21,321,937","daily_vaccines":"2,315","country":"Greece","iso":"GR","region":"Europe","last_update":"2022-08-27 15:25:11"},{"confirmed":"4,644,643","daily_confirmed":"1,631","recovered":"0","daily_recovered":"0","deaths":"32,195","daily_deaths":"29","infected":"4,612,448","daily_infected":"1,602","vaccines":"141,891,341","daily_vaccines":"56,307","country":"Thailand","iso":"TH","region":"Asia","last_update":"2022-08-27 15:25:11"},{"confirmed":"4,629,050","daily_confirmed":"968","recovered":"0","daily_recovered":"0","deaths":"11,589","daily_deaths":"0","infected":"4,617,461","daily_infected":"968","vaccines":"18,219,817","daily_vaccines":"42","country":"Israel","iso":"IL","region":"Asia","last_update":"2022-08-27 15:25:11"},{"confirmed":"4,479,644","daily_confirmed":"8,526","recovered":"0","daily_recovered":"0","deaths":"60,353","daily_deaths":"32","infected":"4,419,291","daily_infected":"8,494","vaccines":"61,834,790","daily_vaccines":"19,855","country":"Chile","iso":"CL","region":"Americas","last_update":"2022-08-27 15:25:11"},{"confirmed":"4,477,770","daily_confirmed":"0","recovered":"0","daily_recovered":"0","deaths":"32,496","daily_deaths":"0","infected":"4,445,274","daily_infected":"0","vaccines":"25,769,971","daily_vaccines":"0","country":"Belgium","iso":"BE","region":"Europe","last_update":"2022-08-27 15:25:11"},{"confirmed":"4,187,139","daily_confirmed":"3,977","recovered":"0","daily_recovered":"0","deaths":"44,049","daily_deaths":"46","infected":"4,143,090","daily_infected":"3,931","vaccines":"88,472,573","daily_vaccines":"22,946","country":"Canada","iso":"CA","region":"Americas","last_update":"2022-08-27 15:25:11"},{"confirmed":"4,094,652","daily_confirmed":"3,286","recovered":"0","daily_recovered":"0","deaths":"215,556","daily_deaths":"42","infected":"3,879,096","daily_infected":"3,244","vaccines":"82,366,473","daily_vaccines":"0","country":"Peru","iso":"PE","region":"Americas","last_update":"2022-08-27 15:25:11"},{"confirmed":"4,035,191","daily_confirmed":"3,488","recovered":"0","daily_recovered":"0","deaths":"40,781","daily_deaths":"23","infected":"3,994,410","daily_infected":"3,465","vaccines":"17,891,099","daily_vaccines":"8,335","country":"Czechia","iso":"CZ","region":"Europe","last_update":"2022-08-27 15:25:11"},{"confirmed":"4,029,657","daily_confirmed":"0","recovered":"0","daily_recovered":"0","deaths":"13,966","daily_deaths":"0","infected":"4,015,691","daily_infected":"0","vaccines":"15,956,438","daily_vaccines":"0","country":"Switzerland","iso":"CH","region":"Europe","last_update":"2022-08-27 15:25:11"},{"confirmed":"4,010,999","daily_confirmed":"247","recovered":"0","daily_recovered":"0","deaths":"102,084","daily_deaths":"0","infected":"3,908,915","daily_infected":"247","vaccines":"37,425,711","daily_vaccines":"11,437","country":"South Africa","iso":"ZA","region":"Africa","last_update":"2022-08-27 15:25:11"},{"confirmed":"3,869,976","daily_confirmed":"2,905","recovered":"0","daily_recovered":"0","deaths":"61,559","daily_deaths":"40","infected":"3,808,417","daily_infected":"2,865","vaccines":"161,174,158","daily_vaccines":"0","country":"Philippines","iso":"PH","region":"Asia","last_update":"2022-08-27 15:25:11"},{"confirmed":"3,315,957","daily_confirmed":"941","recovered":"0","daily_recovered":"0","deaths":"6,942","daily_deaths":"5","infected":"3,309,015","daily_infected":"936","vaccines":"13,210,001","daily_vaccines":"0","country":"Denmark","iso":"DK","region":"Europe","last_update":"2022-08-27 15:25:11"},{"confirmed":"3,206,185","daily_confirmed":"3,319","recovered":"0","daily_recovered":"0","deaths":"66,612","daily_deaths":"16","infected":"3,139,573","daily_infected":"3,303","vaccines":"16,827,486","daily_vaccines":"0","country":"Romania","iso":"RO","region":"Europe","last_update":"2022-08-27 15:25:11"},{"confirmed":"2,580,748","daily_confirmed":"0","recovered":"0","daily_recovered":"0","deaths":"20,236","daily_deaths":"0","infected":"2,560,512","daily_infected":"0","vaccines":"7,074,822","daily_vaccines":"0","country":"Slovakia","iso":"SK","region":"Europe","last_update":"2022-08-27 15:25:11"},{"confirmed":"2,564,423","daily_confirmed":"0","recovered":"0","daily_recovered":"0","deaths":"19,810","daily_deaths":"0","infected":"2,544,613","daily_infected":"0","vaccines":"22,881,367","daily_vaccines":"0","country":"Sweden","iso":"SE","region":"Europe","last_update":"2022-08-27 15:25:11"},{"confirmed":"2,456,555","daily_confirmed":"0","recovered":"0","daily_recovered":"0","deaths":"25,343","daily_deaths":"0","infected":"2,431,212","daily_infected":"0","vaccines":"19,097,435","daily_vaccines":"0","country":"Iraq","iso":"IQ","region":"Asia","last_update":"2022-08-27 15:25:11"},{"confirmed":"2,443,816","daily_confirmed":"8,218","recovered":"0","daily_recovered":"0","deaths":"14,882","daily_deaths":"7","infected":"2,428,934","daily_infected":"8,211","vaccines":"3,431,560,000","daily_vaccines":"313,000","country":"China","iso":"CN","region":"Asia","last_update":"2022-08-27 15:25:11"},{"confirmed":"2,265,924","daily_confirmed":"4,025","recovered":"0","daily_recovered":"0","deaths":"16,616","daily_deaths":"23","infected":"2,249,308","daily_infected":"4,002","vaccines":"8,534,688","daily_vaccines":"0","country":"Serbia","iso":"RS","region":"Europe","last_update":"2022-08-27 15:25:11"},{"confirmed":"2,036,390","daily_confirmed":"0","recovered":"0","daily_recovered":"0","deaths":"47,191","daily_deaths":"0","infected":"1,989,199","daily_infected":"0","vaccines":"16,530,488","daily_vaccines":"0","country":"Hungary","iso":"HU","region":"Europe","last_update":"2022-08-27 15:25:11"},{"confirmed":"2,010,944","daily_confirmed":"196","recovered":"0","daily_recovered":"0","deaths":"29,321","daily_deaths":"1","infected":"1,981,623","daily_infected":"195","vaccines":"293,246,060","daily_vaccines":"0","country":"Bangladesh","iso":"BD","region":"Asia","last_update":"2022-08-27 15:25:11"},{"confirmed":"1,829,361","daily_confirmed":"2,132","recovered":"0","daily_recovered":"0","deaths":"1,588","daily_deaths":"1","infected":"1,827,773","daily_infected":"2,131","vaccines":"14,304,654","daily_vaccines":"0","country":"Singapore","iso":"SG","region":"Asia","last_update":"2022-08-27 15:25:11"},{"confirmed":"1,739,030","daily_confirmed":"2,271","recovered":"0","daily_recovered":"0","deaths":"1,870","daily_deaths":"4","infected":"1,737,160","daily_infected":"2,267","vaccines":"11,650,867","daily_vaccines":"0","country":"New Zealand","iso":"NZ","region":"Oceania","last_update":"2022-08-27 15:25:11"},{"confirmed":"1,735,682","daily_confirmed":"0","recovered":"0","daily_recovered":"0","deaths":"16,889","daily_deaths":"0","infected":"1,718,793","daily_infected":"0","vaccines":"2,921,949","daily_vaccines":"0","country":"Georgia","iso":"GE","region":"Asia","last_update":"2022-08-27 15:25:11"},{"confirmed":"1,731,549","daily_confirmed":"0","recovered":"0","daily_recovered":"0","deaths":"14,105","daily_deaths":"0","infected":"1,717,444","daily_infected":"0","vaccines":"10,057,975","daily_vaccines":"0","country":"Jordan","iso":"JO","region":"Asia","last_update":"2022-08-27 15:25:11"},{"confirmed":"1,655,338","daily_confirmed":"0","recovered":"0","daily_recovered":"0","deaths":"7,820","daily_deaths":"0","infected":"1,647,518","daily_infected":"0","vaccines":"11,026,753","daily_vaccines":"0","country":"Ireland","iso":"IE","region":"Europe","last_update":"2022-08-27 15:25:11"},{"confirmed":"1,568,183","daily_confirmed":"290","recovered":"0","daily_recovered":"0","deaths":"30,571","daily_deaths":"2","infected":"1,537,612","daily_infected":"288","vaccines":"291,747,444","daily_vaccines":"0","country":"Pakistan","iso":"PK","region":"Asia","last_update":"2022-08-27 15:25:11"},{"confirmed":"1,476,288","daily_confirmed":"673","recovered":"0","daily_recovered":"0","deaths":"19,040","daily_deaths":"0","infected":"1,457,248","daily_infected":"673","vaccines":"20,918,681","daily_vaccines":"0","country":"Kazakhstan","iso":"KZ","region":"Asia","last_update":"2022-08-27 15:25:11"},{"confirmed":"1,459,661","daily_confirmed":"135","recovered":"0","daily_recovered":"0","deaths":"3,953","daily_deaths":"0","infected":"1,455,708","daily_infected":"135","vaccines":"11,686,596","daily_vaccines":"0","country":"Norway","iso":"NO","region":"Europe","last_update":"2022-08-27 15:25:11"},{"confirmed":"1,264,237","daily_confirmed":"37","recovered":"0","daily_recovered":"0","deaths":"16,271","daily_deaths":"0","infected":"1,247,966","daily_infected":"37","vaccines":"55,141,078","daily_vaccines":"0","country":"Morocco","iso":"MA","region":"Africa","last_update":"2022-08-27 15:25:11"},{"confirmed":"1,258,798","daily_confirmed":"0","recovered":"0","daily_recovered":"0","deaths":"5,577","daily_deaths":"0","infected":"1,253,221","daily_infected":"0","vaccines":"12,591,177","daily_vaccines":"0","country":"Finland","iso":"FI","region":"Europe","last_update":"2022-08-27 15:25:11"},{"confirmed":"1,239,382","daily_confirmed":"851","recovered":"0","daily_recovered":"0","deaths":"37,584","daily_deaths":"6","infected":"1,201,798","daily_infected":"845","vaccines":"4,519,761","daily_vaccines":"1,388","country":"Bulgaria","iso":"BG","region":"Europe","last_update":"2022-08-27 15:25:11"},{"confirmed":"1,214,484","daily_confirmed":"964","recovered":"0","daily_recovered":"0","deaths":"9,276","daily_deaths":"6","infected":"1,205,208","daily_infected":"958","vaccines":"4,497,253","daily_vaccines":"221","country":"Lithuania","iso":"LT","region":"Europe","last_update":"2022-08-27 15:25:11"},{"confirmed":"1,210,431","daily_confirmed":"851","recovered":"0","daily_recovered":"0","deaths":"16,639","daily_deaths":"17","infected":"1,193,792","daily_infected":"834","vaccines":"5,269,665","daily_vaccines":"0","country":"Croatia","iso":"HR","region":"Europe","last_update":"2022-08-27 15:25:11"},{"confirmed":"1,207,385","daily_confirmed":"628","recovered":"0","daily_recovered":"0","deaths":"10,617","daily_deaths":"2","infected":"1,196,768","daily_infected":"626","vaccines":"5,746,016","daily_vaccines":"0","country":"Lebanon","iso":"LB","region":"Asia","last_update":"2022-08-27 15:25:11"},{"confirmed":"1,143,167","daily_confirmed":"374","recovered":"0","daily_recovered":"0","deaths":"29,233","daily_deaths":"4","infected":"1,113,934","daily_infected":"370","vaccines":"14,916,574","daily_vaccines":"0","country":"Tunisia","iso":"TN","region":"Africa","last_update":"2022-08-27 15:25:11"},{"confirmed":"1,120,443","daily_confirmed":"1,902","recovered":"0","daily_recovered":"0","deaths":"6,771","daily_deaths":"4","infected":"1,113,672","daily_infected":"1,898","vaccines":"2,996,643","daily_vaccines":"0","country":"Slovenia","iso":"SI","region":"Europe","last_update":"2022-08-27 15:25:11"},{"confirmed":"1,110,277","daily_confirmed":"59","recovered":"0","daily_recovered":"0","deaths":"8,530","daily_deaths":"0","infected":"1,101,747","daily_infected":"59","vaccines":"40,908,750","daily_vaccines":"0","country":"Cuba","iso":"CU","region":"Americas","last_update":"2022-08-27 15:25:11"},{"confirmed":"1,098,027","daily_confirmed":"1,183","recovered":"0","daily_recovered":"0","deaths":"22,186","daily_deaths":"3","infected":"1,075,841","daily_infected":"1,180","vaccines":"14,332,894","daily_vaccines":"0","country":"Bolivia","iso":"BO","region":"Americas","last_update":"2022-08-27 15:25:11"},{"confirmed":"1,094,572","daily_confirmed":"2,027","recovered":"0","daily_recovered":"0","deaths":"19,424","daily_deaths":"20","infected":"1,075,148","daily_infected":"2,007","vaccines":"19,281,914","daily_vaccines":"96,513","country":"Guatemala","iso":"GT","region":"Americas","last_update":"2022-08-27 15:25:11"},{"confirmed":"1,079,825","daily_confirmed":"0","recovered":"0","daily_recovered":"0","deaths":"8,836","daily_deaths":"0","infected":"1,070,989","daily_infected":"0","vaccines":"11,703,991","daily_vaccines":"0","country":"Costa Rica","iso":"CR","region":"Americas","last_update":"2022-08-27 15:25:11"},{"confirmed":"1,012,786","daily_confirmed":"580","recovered":"0","daily_recovered":"0","deaths":"2,341","daily_deaths":"0","infected":"1,010,445","daily_infected":"580","vaccines":"24,922,054","daily_vaccines":"0","country":"United Arab Emirates","iso":"AE","region":"Asia","last_update":"2022-08-27 15:25:11"},{"confirmed":"996,605","daily_confirmed":"163","recovered":"0","daily_recovered":"0","deaths":"11,999","daily_deaths":"1","infected":"984,606","daily_infected":"162","vaccines":"53,747,378","daily_vaccines":"0","country":"Nepal","iso":"NP","region":"Asia","last_update":"2022-08-27 15:25:11"},{"confirmed":"994,037","daily_confirmed":"0","recovered":"0","daily_recovered":"0","deaths":"7,118","daily_deaths":"0","infected":"986,919","daily_infected":"0","vaccines":"14,916,985","daily_vaccines":"0","country":"Belarus","iso":"BY","region":"Europe","last_update":"2022-08-27 15:25:11"},{"confirmed":"993,858","daily_confirmed":"1,020","recovered":"0","daily_recovered":"0","deaths":"35,830","daily_deaths":"6","infected":"958,028","daily_infected":"1,014","vaccines":"37,260,948","daily_vaccines":"0","country":"Ecuador","iso":"EC","region":"Americas","last_update":"2022-08-27 15:25:11"},{"confirmed":"977,305","daily_confirmed":"0","recovered":"0","daily_recovered":"0","deaths":"7,438","daily_deaths":"0","infected":"969,867","daily_infected":"0","vaccines":"8,726,633","daily_vaccines":"546","country":"Uruguay","iso":"UY","region":"Americas","last_update":"2022-08-27 15:25:11"},{"confirmed":"976,751","daily_confirmed":"0","recovered":"0","daily_recovered":"0","deaths":"2,125","daily_deaths":"0","infected":"974,626","daily_infected":"0","vaccines":"5,492,919","daily_vaccines":"0","country":"Mongolia","iso":"MN","region":"Asia","last_update":"2022-08-27 15:25:11"},{"confirmed":"972,800","daily_confirmed":"0","recovered":"0","daily_recovered":"0","deaths":"8,456","daily_deaths":"0","infected":"964,344","daily_infected":"0","vaccines":"8,538,113","daily_vaccines":"0","country":"Panama","iso":"PA","region":"Americas","last_update":"2022-08-27 15:25:11"},{"confirmed":"895,513","daily_confirmed":"994","recovered":"0","daily_recovered":"0","deaths":"5,937","daily_deaths":"2","infected":"889,576","daily_infected":"992","vaccines":"2,895,716","daily_vaccines":"0","country":"Latvia","iso":"LV","region":"Europe","last_update":"2022-08-27 15:25:11"},{"confirmed":"813,042","daily_confirmed":"67","recovered":"0","daily_recovered":"0","deaths":"9,287","daily_deaths":"3","infected":"803,755","daily_infected":"64","vaccines":"67,577,413","daily_vaccines":"0","country":"Saudi Arabia","iso":"SA","region":"Asia","last_update":"2022-08-27 15:25:11"},{"confirmed":"811,131","daily_confirmed":"542","recovered":"0","daily_recovered":"0","deaths":"9,796","daily_deaths":"1","infected":"801,335","daily_infected":"541","vaccines":"13,853,207","daily_vaccines":"0","country":"Azerbaijan","iso":"AZ","region":"Asia","last_update":"2022-08-27 15:25:11"},{"confirmed":"715,162","daily_confirmed":"822","recovered":"0","daily_recovered":"0","deaths":"19,478","daily_deaths":"30","infected":"695,684","daily_infected":"792","vaccines":"9,313,856","daily_vaccines":"0","country":"Paraguay","iso":"PY","region":"Americas","last_update":"2022-08-27 15:25:11"},{"confirmed":"698,384","daily_confirmed":"0","recovered":"0","daily_recovered":"0","deaths":"5,694","daily_deaths":"0","infected":"692,690","daily_infected":"0","vaccines":"0","daily_vaccines":"0","country":"West Bank and Gaza","iso":"PS","region":"Asia","last_update":"2022-08-27 15:25:11"},{"confirmed":"670,717","daily_confirmed":"140","recovered":"0","daily_recovered":"0","deaths":"1,513","daily_deaths":"0","infected":"669,204","daily_infected":"140","vaccines":"3,466,610","daily_vaccines":"73","country":"Bahrain","iso":"BH","region":"Asia","last_update":"2022-08-27 15:25:11"},{"confirmed":"669,639","daily_confirmed":"58","recovered":"0","daily_recovered":"0","deaths":"16,679","daily_deaths":"4","infected":"652,960","daily_infected":"54","vaccines":"39,735,513","daily_vaccines":"0","country":"Sri Lanka","iso":"LK","region":"Asia","last_update":"2022-08-27 15:25:11"},{"confirmed":"657,042","daily_confirmed":"0","recovered":"0","daily_recovered":"0","deaths":"2,563","daily_deaths":"0","infected":"654,479","daily_infected":"0","vaccines":"8,193,294","daily_vaccines":"0","country":"Kuwait","iso":"KW","region":"Asia","last_update":"2022-08-27 15:25:11"},{"confirmed":"637,573","daily_confirmed":"0","recovered":"0","daily_recovered":"0","deaths":"4,384","daily_deaths":"0","infected":"633,189","daily_infected":"0","vaccines":"15,952,103","daily_vaccines":"0","country":"Dominican Republic","iso":"DO","region":"Americas","last_update":"2022-08-27 15:25:11"},{"confirmed":"614,573","daily_confirmed":"0","recovered":"0","daily_recovered":"0","deaths":"19,437","daily_deaths":"0","infected":"595,136","daily_infected":"0","vaccines":"0","daily_vaccines":"0","country":"Burma","iso":"MM","region":"Asia","last_update":"2022-08-27 15:25:11"},{"confirmed":"596,763","daily_confirmed":"0","recovered":"0","daily_recovered":"0","deaths":"2,647","daily_deaths":"0","infected":"594,116","daily_infected":"0","vaccines":"2,020,205","daily_vaccines":"0","country":"Estonia","iso":"EE","region":"Europe","last_update":"2022-08-27 15:25:11"},{"confirmed":"576,278","daily_confirmed":"2,154","recovered":"0","daily_recovered":"0","deaths":"1,168","daily_deaths":"16","infected":"575,110","daily_infected":"2,138","vaccines":"1,792,897","daily_vaccines":"0","country":"Cyprus","iso":"CY","region":"Asia","last_update":"2022-08-27 15:25:11"},{"confirmed":"569,088","daily_confirmed":"0","recovered":"0","daily_recovered":"0","deaths":"11,725","daily_deaths":"0","infected":"557,363","daily_infected":"0","vaccines":"2,165,600","daily_vaccines":"0","country":"Moldova","iso":"MD","region":"Europe","last_update":"2022-08-27 15:25:11"},{"confirmed":"542,039","daily_confirmed":"232","recovered":"0","daily_recovered":"0","deaths":"5,794","daily_deaths":"2","infected":"536,245","daily_infected":"230","vaccines":"37,860,994","daily_vaccines":"0","country":"Venezuela","iso":"VE","region":"Americas","last_update":"2022-08-27 15:25:11"},{"confirmed":"515,645","daily_confirmed":"0","recovered":"0","daily_recovered":"0","deaths":"24,791","daily_deaths":"0","infected":"490,854","daily_infected":"0","vaccines":"97,076,742","daily_vaccines":"0","country":"Egypt","iso":"EG","region":"Africa","last_update":"2022-08-27 15:25:11"},{"confirmed":"506,746","daily_confirmed":"41","recovered":"0","daily_recovered":"0","deaths":"6,436","daily_deaths":"0","infected":"500,310","daily_infected":"41","vaccines":"3,693,986","daily_vaccines":"0","country":"Libya","iso":"LY","region":"Africa","last_update":"2022-08-27 15:25:11"},{"confirmed":"493,132","daily_confirmed":"43","recovered":"0","daily_recovered":"0","deaths":"7,571","daily_deaths":"0","infected":"485,561","daily_infected":"43","vaccines":"52,509,414","daily_vaccines":"0","country":"Ethiopia","iso":"ET","region":"Africa","last_update":"2022-08-27 15:25:11"},{"confirmed":"452,305","daily_confirmed":"0","recovered":"0","daily_recovered":"0","deaths":"10,972","daily_deaths":"0","infected":"441,333","daily_infected":"0","vaccines":"15,177,956","daily_vaccines":"157,617","country":"Honduras","iso":"HN","region":"Americas","last_update":"2022-08-27 15:25:11"},{"confirmed":"432,274","daily_confirmed":"0","recovered":"0","daily_recovered":"0","deaths":"8,648","daily_deaths":"0","infected":"423,626","daily_infected":"0","vaccines":"2,150,112","daily_vaccines":"0","country":"Armenia","iso":"AM","region":"Asia","last_update":"2022-08-27 15:25:11"},{"confirmed":"426,586","daily_confirmed":"503","recovered":"0","daily_recovered":"0","deaths":"681","daily_deaths":"0","infected":"425,905","daily_infected":"503","vaccines":"7,367,403","daily_vaccines":"0","country":"Qatar","iso":"QA","region":"Asia","last_update":"2022-08-27 15:25:11"},{"confirmed":"397,846","daily_confirmed":"0","recovered":"0","daily_recovered":"0","deaths":"4,628","daily_deaths":"0","infected":"393,218","daily_infected":"0","vaccines":"7,089,974","daily_vaccines":"0","country":"Oman","iso":"OM","region":"Asia","last_update":"2022-08-27 15:25:11"},{"confirmed":"395,086","daily_confirmed":"220","recovered":"0","daily_recovered":"0","deaths":"16,026","daily_deaths":"5","infected":"379,060","daily_infected":"215","vaccines":"1,924,950","daily_vaccines":"0","country":"Bosnia and Herzegovina","iso":"BA","region":"Europe","last_update":"2022-08-27 15:25:11"},{"confirmed":"339,492","daily_confirmed":"252","recovered":"0","daily_recovered":"0","deaths":"9,473","daily_deaths":"5","infected":"330,019","daily_infected":"247","vaccines":"1,860,276","daily_vaccines":"0","country":"North Macedonia","iso":"MK","region":"Europe","last_update":"2022-08-27 15:25:11"},{"confirmed":"338,105","daily_confirmed":"12","recovered":"0","daily_recovered":"0","deaths":"5,673","daily_deaths":"0","infected":"332,432","daily_infected":"12","vaccines":"20,920,745","daily_vaccines":"0","country":"Kenya","iso":"KE","region":"Africa","last_update":"2022-08-27 15:25:11"},{"confirmed":"332,710","daily_confirmed":"0","recovered":"0","daily_recovered":"0","deaths":"4,016","daily_deaths":"0","infected":"328,694","daily_infected":"0","vaccines":"8,830,640","daily_vaccines":"0","country":"Zambia","iso":"ZM","region":"Africa","last_update":"2022-08-27 15:25:11"},{"confirmed":"327,961","daily_confirmed":"354","recovered":"0","daily_recovered":"0","deaths":"3,580","daily_deaths":"1","infected":"324,381","daily_infected":"353","vaccines":"2,956,198","daily_vaccines":"0","country":"Albania","iso":"AL","region":"Europe","last_update":"2022-08-27 15:25:11"},{"confirmed":"325,864","daily_confirmed":"0","recovered":"0","daily_recovered":"0","deaths":"2,778","daily_deaths":"0","infected":"323,086","daily_infected":"0","vaccines":"2,871,301","daily_vaccines":"0","country":"Botswana","iso":"BW","region":"Africa","last_update":"2022-08-27 15:25:11"},{"confirmed":"286,289","daily_confirmed":"101","recovered":"0","daily_recovered":"0","deaths":"1,122","daily_deaths":"0","infected":"285,167","daily_infected":"101","vaccines":"1,339,825","daily_vaccines":"0","country":"Luxembourg","iso":"LU","region":"Europe","last_update":"2022-08-27 15:25:11"},{"confirmed":"274,491","daily_confirmed":"273","recovered":"0","daily_recovered":"0","deaths":"2,770","daily_deaths":"0","infected":"271,721","daily_infected":"273","vaccines":"679,171","daily_vaccines":"373","country":"Montenegro","iso":"ME","region":"Europe","last_update":"2022-08-27 15:25:11"},{"confirmed":"270,897","daily_confirmed":"188","recovered":"0","daily_recovered":"0","deaths":"3,191","daily_deaths":"0","infected":"267,706","daily_infected":"188","vaccines":"1,835,493","daily_vaccines":"35","country":"Kosovo","iso":"XK","region":"XK","last_update":"2022-08-27 15:25:11"},{"confirmed":"270,145","daily_confirmed":"48","recovered":"0","daily_recovered":"0","deaths":"6,878","daily_deaths":"0","infected":"263,267","daily_infected":"48","vaccines":"15,205,854","daily_vaccines":"0","country":"Algeria","iso":"DZ","region":"Africa","last_update":"2022-08-27 15:25:11"},{"confirmed":"263,322","daily_confirmed":"0","recovered":"0","daily_recovered":"0","deaths":"3,148","daily_deaths":"0","infected":"260,174","daily_infected":"0","vaccines":"63,346,714","daily_vaccines":"0","country":"Nigeria","iso":"NG","region":"Africa","last_update":"2022-08-27 15:25:11"},{"confirmed":"256,682","daily_confirmed":"7","recovered":"0","daily_recovered":"0","deaths":"5,593","daily_deaths":"0","infected":"251,089","daily_infected":"7","vaccines":"12,182,698","daily_vaccines":"0","country":"Zimbabwe","iso":"ZW","region":"Africa","last_update":"2022-08-27 15:25:11"},{"confirmed":"254,400","daily_confirmed":"0","recovered":"0","daily_recovered":"0","deaths":"1,022","daily_deaths":"2","infected":"253,378","daily_infected":"-2","vaccines":"2,572,824","daily_vaccines":"0","country":"Mauritius","iso":"MU","region":"Africa","last_update":"2022-08-27 15:25:11"},{"confirmed":"243,743","daily_confirmed":"15","recovered":"0","daily_recovered":"0","deaths":"1,637","daily_deaths":"0","infected":"242,106","daily_infected":"15","vaccines":"63,619,811","daily_vaccines":"0","country":"Uzbekistan","iso":"UZ","region":"Asia","last_update":"2022-08-27 15:25:11"},{"confirmed":"230,053","daily_confirmed":"34","recovered":"0","daily_recovered":"0","deaths":"2,219","daily_deaths":"0","infected":"227,834","daily_infected":"34","vaccines":"24,069,038","daily_vaccines":"0","country":"Mozambique","iso":"MZ","region":"Africa","last_update":"2022-08-27 15:25:11"},{"confirmed":"220,245","daily_confirmed":"0","recovered":"0","daily_recovered":"0","deaths":"225","daily_deaths":"0","infected":"220,020","daily_infected":"0","vaccines":"1,259,753","daily_vaccines":"0","country":"Brunei","iso":"BN","region":"Asia","last_update":"2022-08-27 15:25:11"},{"confirmed":"213,691","daily_confirmed":"100","recovered":"0","daily_recovered":"0","deaths":"757","daily_deaths":"0","infected":"212,934","daily_infected":"100","vaccines":"11,111,066","daily_vaccines":"0","country":"Laos","iso":"LA","region":"Asia","last_update":"2022-08-27 15:25:11"},{"confirmed":"205,537","daily_confirmed":"0","recovered":"0","daily_recovered":"0","deaths":"2,991","daily_deaths":"0","infected":"202,546","daily_infected":"0","vaccines":"3,200,369","daily_vaccines":"1,715","country":"Kyrgyzstan","iso":"KG","region":"Asia","last_update":"2022-08-27 15:25:11"},{"confirmed":"204,268","daily_confirmed":"0","recovered":"0","daily_recovered":"0","deaths":"179","daily_deaths":"0","infected":"204,089","daily_infected":"0","vaccines":"805,469","daily_vaccines":"0","country":"Iceland","iso":"IS","region":"Europe","last_update":"2022-08-27 15:25:11"},{"confirmed":"191,967","daily_confirmed":"0","recovered":"0","daily_recovered":"0","deaths":"7,771","daily_deaths":"0","infected":"184,196","daily_infected":"0","vaccines":"11,391,703","daily_vaccines":"0","country":"Afghanistan","iso":"AF","region":"Asia","last_update":"2022-08-27 15:25:11"},{"confirmed":"190,818","daily_confirmed":"0","recovered":"0","daily_recovered":"0","deaths":"4,221","daily_deaths":"0","infected":"186,597","daily_infected":"0","vaccines":"11,127,982","daily_vaccines":"0","country":"El Salvador","iso":"SV","region":"Americas","last_update":"2022-08-27 15:25:11"},{"confirmed":"184,788","daily_confirmed":"0","recovered":"0","daily_recovered":"0","deaths":"307","daily_deaths":"0","infected":"184,481","daily_infected":"0","vaccines":"950,159","daily_vaccines":"0","country":"Maldives","iso":"MV","region":"Asia","last_update":"2022-08-27 15:25:11"},{"confirmed":"178,111","daily_confirmed":"287","recovered":"0","daily_recovered":"0","deaths":"4,123","daily_deaths":"4","infected":"173,988","daily_infected":"283","vaccines":"1,579,374","daily_vaccines":"94","country":"Trinidad and Tobago","iso":"TT","region":"Americas","last_update":"2022-08-27 15:25:11"},{"confirmed":"169,396","daily_confirmed":"0","recovered":"0","daily_recovered":"0","deaths":"3,628","daily_deaths":"0","infected":"165,768","daily_infected":"0","vaccines":"25,078,754","daily_vaccines":"0","country":"Uganda","iso":"UG","region":"Africa","last_update":"2022-08-27 15:25:11"},{"confirmed":"169,253","daily_confirmed":"0","recovered":"0","daily_recovered":"0","deaths":"4,074","daily_deaths":"0","infected":"165,179","daily_infected":"0","vaccines":"933,619","daily_vaccines":"0","country":"Namibia","iso":"NA","region":"NA","last_update":"2022-08-27 15:25:11"},{"confirmed":"168,565","daily_confirmed":"108","recovered":"0","daily_recovered":"0","deaths":"1,459","daily_deaths":"0","infected":"167,106","daily_infected":"108","vaccines":"18,396,070","daily_vaccines":"0","country":"Ghana","iso":"GH","region":"Africa","last_update":"2022-08-27 15:25:11"},{"confirmed":"149,327","daily_confirmed":"109","recovered":"0","daily_recovered":"0","deaths":"3,241","daily_deaths":"2","infected":"146,086","daily_infected":"107","vaccines":"1,480,367","daily_vaccines":"0","country":"Jamaica","iso":"JM","region":"Americas","last_update":"2022-08-27 15:25:11"},{"confirmed":"137,519","daily_confirmed":"22","recovered":"0","daily_recovered":"0","deaths":"3,056","daily_deaths":"0","infected":"134,463","daily_infected":"22","vaccines":"42,893,177","daily_vaccines":"0","country":"Cambodia","iso":"KH","region":"Asia","last_update":"2022-08-27 15:25:11"},{"confirmed":"132,412","daily_confirmed":"4","recovered":"0","daily_recovered":"0","deaths":"1,466","daily_deaths":"0","infected":"130,946","daily_infected":"4","vaccines":"26,054,302","daily_vaccines":"0","country":"Rwanda","iso":"RW","region":"Africa","last_update":"2022-08-27 15:25:11"},{"confirmed":"121,652","daily_confirmed":"685","recovered":"0","daily_recovered":"0","deaths":"1,935","daily_deaths":"2","infected":"119,717","daily_infected":"683","vaccines":"1,854,436","daily_vaccines":"0","country":"Cameroon","iso":"CM","region":"Africa","last_update":"2022-08-27 15:25:11"},{"confirmed":"113,916","daily_confirmed":"0","recovered":"0","daily_recovered":"0","deaths":"799","daily_deaths":"0","infected":"113,117","daily_infected":"0","vaccines":"1,334,020","daily_vaccines":"0","country":"Malta","iso":"MT","region":"Europe","last_update":"2022-08-27 15:25:11"},{"confirmed":"102,636","daily_confirmed":"0","recovered":"0","daily_recovered":"0","deaths":"1,917","daily_deaths":"0","infected":"100,719","daily_infected":"0","vaccines":"22,120,543","daily_vaccines":"0","country":"Angola","iso":"AO","region":"Africa","last_update":"2022-08-27 15:25:11"},{"confirmed":"100,526","daily_confirmed":"153","recovered":"0","daily_recovered":"0","deaths":"537","daily_deaths":"0","infected":"99,989","daily_infected":"153","vaccines":"317,519","daily_vaccines":"0","country":"Barbados","iso":"BB","region":"Americas","last_update":"2022-08-27 15:25:11"},{"confirmed":"92,634","daily_confirmed":"46","recovered":"0","daily_recovered":"0","deaths":"1,400","daily_deaths":"4","infected":"91,234","daily_infected":"42","vaccines":"0","daily_vaccines":"0","country":"Congo (Kinshasa)","iso":"CD","region":"Africa","last_update":"2022-08-27 15:25:11"},{"confirmed":"88,008","daily_confirmed":"21","recovered":"0","daily_recovered":"0","deaths":"1,968","daily_deaths":"0","infected":"86,040","daily_infected":"21","vaccines":"2,469,499","daily_vaccines":"0","country":"Senegal","iso":"SN","region":"Africa","last_update":"2022-08-27 15:25:11"},{"confirmed":"87,828","daily_confirmed":"14","recovered":"0","daily_recovered":"0","deaths":"2,676","daily_deaths":"0","infected":"85,152","daily_infected":"14","vaccines":"4,121,001","daily_vaccines":"0","country":"Malawi","iso":"MW","region":"Africa","last_update":"2022-08-27 15:25:11"},{"confirmed":"86,577","daily_confirmed":"35","recovered":"0","daily_recovered":"0","deaths":"817","daily_deaths":"0","infected":"85,760","daily_infected":"35","vaccines":"18,035,554","daily_vaccines":"0","country":"Cote d'Ivoire","iso":"CI","region":"Africa","last_update":"2022-08-27 15:25:11"},{"confirmed":"81,022","daily_confirmed":"0","recovered":"0","daily_recovered":"0","deaths":"1,383","daily_deaths":"0","infected":"79,639","daily_infected":"0","vaccines":"505,699","daily_vaccines":"0","country":"Suriname","iso":"SR","region":"Americas","last_update":"2022-08-27 15:25:11"},{"confirmed":"73,358","daily_confirmed":"5","recovered":"0","daily_recovered":"0","deaths":"1,422","daily_deaths":"0","infected":"71,936","daily_infected":"5","vaccines":"764,657","daily_vaccines":"0","country":"Eswatini","iso":"SZ","region":"Africa","last_update":"2022-08-27 15:25:11"},{"confirmed":"70,943","daily_confirmed":"17","recovered":"0","daily_recovered":"0","deaths":"1,278","daily_deaths":"0","infected":"69,665","daily_infected":"17","vaccines":"1,017,969","daily_vaccines":"0","country":"Guyana","iso":"GY","region":"Americas","last_update":"2022-08-27 15:25:11"},{"confirmed":"68,187","daily_confirmed":"76","recovered":"0","daily_recovered":"0","deaths":"680","daily_deaths":"0","infected":"67,507","daily_infected":"76","vaccines":"498,175","daily_vaccines":"472","country":"Belize","iso":"BZ","region":"Americas","last_update":"2022-08-27 15:25:11"},{"confirmed":"68,116","daily_confirmed":"0","recovered":"0","daily_recovered":"0","deaths":"877","daily_deaths":"0","infected":"67,239","daily_infected":"0","vaccines":"1,531,333","daily_vaccines":"0","country":"Fiji","iso":"FJ","region":"Oceania","last_update":"2022-08-27 15:25:11"},{"confirmed":"66,615","daily_confirmed":"0","recovered":"0","daily_recovered":"0","deaths":"1,410","daily_deaths":"0","infected":"65,205","daily_infected":"0","vaccines":"1,735,843","daily_vaccines":"0","country":"Madagascar","iso":"MG","region":"Africa","last_update":"2022-08-27 15:25:11"},{"confirmed":"63,173","daily_confirmed":"0","recovered":"0","daily_recovered":"0","deaths":"4,961","daily_deaths":"0","infected":"58,212","daily_infected":"0","vaccines":"8,179,010","daily_vaccines":"0","country":"Sudan","iso":"SD","region":"Africa","last_update":"2022-08-27 15:25:11"},{"confirmed":"62,756","daily_confirmed":"0","recovered":"0","daily_recovered":"0","deaths":"992","daily_deaths":"0","infected":"61,764","daily_infected":"0","vaccines":"3,085,578","daily_vaccines":"0","country":"Mauritania","iso":"MR","region":"Africa","last_update":"2022-08-27 15:25:11"},{"confirmed":"62,306","daily_confirmed":"5","recovered":"0","daily_recovered":"0","deaths":"410","daily_deaths":"0","infected":"61,896","daily_infected":"5","vaccines":"0","daily_vaccines":"0","country":"Cabo Verde","iso":"CV","region":"Africa","last_update":"2022-08-27 15:25:11"},{"confirmed":"60,898","daily_confirmed":"0","recovered":"0","daily_recovered":"0","deaths":"21","daily_deaths":"0","infected":"60,877","daily_infected":"0","vaccines":"1,922,660","daily_vaccines":"0","country":"Bhutan","iso":"BT","region":"Asia","last_update":"2022-08-27 15:25:11"},{"confirmed":"56,969","daily_confirmed":"22","recovered":"0","daily_recovered":"0","deaths":"3,163","daily_deaths":"1","infected":"53,806","daily_infected":"21","vaccines":"4,553,467","daily_vaccines":"0","country":"Syria","iso":"SY","region":"Asia","last_update":"2022-08-27 15:25:11"},{"confirmed":"49,063","daily_confirmed":"0","recovered":"0","daily_recovered":"0","deaths":"38","daily_deaths":"0","infected":"49,025","daily_infected":"0","vaccines":"39,833","daily_vaccines":"0","country":"Burundi","iso":"BI","region":"Africa","last_update":"2022-08-27 15:25:11"},{"confirmed":"48,635","daily_confirmed":"0","recovered":"0","daily_recovered":"0","deaths":"306","daily_deaths":"0","infected":"48,329","daily_infected":"0","vaccines":"569,829","daily_vaccines":"0","country":"Gabon","iso":"GA","region":"Africa","last_update":"2022-08-27 15:25:11"},{"confirmed":"46,027","daily_confirmed":"0","recovered":"0","daily_recovered":"0","deaths":"154","daily_deaths":"0","infected":"45,873","daily_infected":"0","vaccines":"154,077","daily_vaccines":"0","country":"Andorra","iso":"AD","region":"Europe","last_update":"2022-08-27 15:25:11"},{"confirmed":"45,852","daily_confirmed":"0","recovered":"0","daily_recovered":"0","deaths":"168","daily_deaths":"0","infected":"45,684","daily_infected":"0","vaccines":"212,980","daily_vaccines":"0","country":"Seychelles","iso":"SC","region":"Africa","last_update":"2022-08-27 15:25:11"},{"confirmed":"44,876","daily_confirmed":"0","recovered":"0","daily_recovered":"0","deaths":"664","daily_deaths":"0","infected":"44,212","daily_infected":"0","vaccines":"647,736","daily_vaccines":"0","country":"Papua New Guinea","iso":"PG","region":"Oceania","last_update":"2022-08-27 15:25:11"},{"confirmed":"38,712","daily_confirmed":"0","recovered":"0","daily_recovered":"0","deaths":"841","daily_deaths":"0","infected":"37,871","daily_infected":"0","vaccines":"22,082,377","daily_vaccines":"0","country":"Tanzania","iso":"TZ","region":"Africa","last_update":"2022-08-27 15:25:11"},{"confirmed":"38,410","daily_confirmed":"16","recovered":"0","daily_recovered":"0","deaths":"282","daily_deaths":"0","infected":"38,128","daily_infected":"16","vaccines":"3,262,548","daily_vaccines":"0","country":"Togo","iso":"TG","region":"Africa","last_update":"2022-08-27 15:25:11"},{"confirmed":"37,470","daily_confirmed":"0","recovered":"0","daily_recovered":"0","deaths":"447","daily_deaths":"0","infected":"37,023","daily_infected":"0","vaccines":"6,603,336","daily_vaccines":"0","country":"Guinea","iso":"GN","region":"Africa","last_update":"2022-08-27 15:25:11"},{"confirmed":"37,044","daily_confirmed":"12","recovered":"0","daily_recovered":"0","deaths":"823","daily_deaths":"0","infected":"36,221","daily_infected":"12","vaccines":"357,101","daily_vaccines":"1,143","country":"Bahamas","iso":"BS","region":"Americas","last_update":"2022-08-27 15:25:11"},{"confirmed":"34,206","daily_confirmed":"0","recovered":"0","daily_recovered":"0","deaths":"704","daily_deaths":"0","infected":"33,502","daily_infected":"0","vaccines":"1,077,116","daily_vaccines":"0","country":"Lesotho","iso":"LS","region":"Africa","last_update":"2022-08-27 15:25:11"},{"confirmed":"33,133","daily_confirmed":"0","recovered":"0","daily_recovered":"0","deaths":"841","daily_deaths":"0","infected":"32,292","daily_infected":"0","vaccines":"362,130","daily_vaccines":"0","country":"Haiti","iso":"HT","region":"Americas","last_update":"2022-08-27 15:25:11"},{"confirmed":"31,302","daily_confirmed":"12","recovered":"0","daily_recovered":"0","deaths":"739","daily_deaths":"0","infected":"30,563","daily_infected":"12","vaccines":"2,894,939","daily_vaccines":"0","country":"Mali","iso":"ML","region":"Africa","last_update":"2022-08-27 15:25:11"},{"confirmed":"28,689","daily_confirmed":"68","recovered":"0","daily_recovered":"0","deaths":"389","daily_deaths":"0","infected":"28,300","daily_infected":"68","vaccines":"122,447","daily_vaccines":"0","country":"Saint Lucia","iso":"LC","region":"Americas","last_update":"2022-08-27 15:25:11"},{"confirmed":"27,316","daily_confirmed":"0","recovered":"0","daily_recovered":"0","deaths":"163","daily_deaths":"0","infected":"27,153","daily_infected":"0","vaccines":"3,685,113","daily_vaccines":"0","country":"Benin","iso":"BJ","region":"Africa","last_update":"2022-08-27 15:25:11"},{"confirmed":"27,020","daily_confirmed":"0","recovered":"0","daily_recovered":"0","deaths":"1,361","daily_deaths":"0","infected":"25,659","daily_infected":"0","vaccines":"4,441,191","daily_vaccines":"0","country":"Somalia","iso":"SO","region":"Africa","last_update":"2022-08-27 15:25:11"},{"confirmed":"24,837","daily_confirmed":"0","recovered":"0","daily_recovered":"0","deaths":"386","daily_deaths":"0","infected":"24,451","daily_infected":"0","vaccines":"0","daily_vaccines":"0","country":"Congo (Brazzaville)","iso":"CG","region":"Africa","last_update":"2022-08-27 15:25:11"},{"confirmed":"23,152","daily_confirmed":"8","recovered":"0","daily_recovered":"0","deaths":"137","daily_deaths":"1","infected":"23,015","daily_infected":"7","vaccines":"0","daily_vaccines":"0","country":"Timor-Leste","iso":"TL","region":"Asia","last_update":"2022-08-27 15:25:11"},{"confirmed":"21,544","daily_confirmed":"0","recovered":"0","daily_recovered":"0","deaths":"153","daily_deaths":"0","infected":"21,391","daily_infected":"0","vaccines":"513,692","daily_vaccines":"0","country":"Solomon Islands","iso":"SB","region":"Oceania","last_update":"2022-08-27 15:25:11"},{"confirmed":"21,128","daily_confirmed":"0","recovered":"0","daily_recovered":"0","deaths":"387","daily_deaths":"0","infected":"20,741","daily_infected":"0","vaccines":"3,474,679","daily_vaccines":"0","country":"Burkina Faso","iso":"BF","region":"Africa","last_update":"2022-08-27 15:25:11"},{"confirmed":"20,323","daily_confirmed":"13","recovered":"0","daily_recovered":"0","deaths":"118","daily_deaths":"0","infected":"20,205","daily_infected":"13","vaccines":"69,338","daily_vaccines":"0","country":"San Marino","iso":"SM","region":"Europe","last_update":"2022-08-27 15:25:11"},{"confirmed":"19,268","daily_confirmed":"0","recovered":"0","daily_recovered":"0","deaths":"236","daily_deaths":"0","infected":"19,032","daily_infected":"0","vaccines":"89,897","daily_vaccines":"49","country":"Grenada","iso":"GD","region":"Americas","last_update":"2022-08-27 15:25:11"},{"confirmed":"19,086","daily_confirmed":"39","recovered":"0","daily_recovered":"0","deaths":"86","daily_deaths":"0","infected":"19,000","daily_infected":"39","vaccines":"71,386","daily_vaccines":"0","country":"Liechtenstein","iso":"LI","region":"Europe","last_update":"2022-08-27 15:25:11"},{"confirmed":"17,823","daily_confirmed":"0","recovered":"0","daily_recovered":"0","deaths":"138","daily_deaths":"0","infected":"17,685","daily_infected":"0","vaccines":"1,656,130","daily_vaccines":"0","country":"South Sudan","iso":"SS","region":"Africa","last_update":"2022-08-27 15:25:11"},{"confirmed":"17,786","daily_confirmed":"0","recovered":"0","daily_recovered":"0","deaths":"125","daily_deaths":"0","infected":"17,661","daily_infected":"0","vaccines":"15,441,380","daily_vaccines":"0","country":"Tajikistan","iso":"TJ","region":"Asia","last_update":"2022-08-27 15:25:11"},{"confirmed":"16,945","daily_confirmed":"7","recovered":"0","daily_recovered":"0","deaths":"183","daily_deaths":"0","infected":"16,762","daily_infected":"7","vaccines":"488,738","daily_vaccines":"0","country":"Equatorial Guinea","iso":"GQ","region":"Africa","last_update":"2022-08-27 15:25:11"},{"confirmed":"15,767","daily_confirmed":"0","recovered":"0","daily_recovered":"0","deaths":"29","daily_deaths":"0","infected":"15,738","daily_infected":"0","vaccines":"503,009","daily_vaccines":"0","country":"Samoa","iso":"WS","region":"Oceania","last_update":"2022-08-27 15:25:11"},{"confirmed":"15,690","daily_confirmed":"0","recovered":"0","daily_recovered":"0","deaths":"189","daily_deaths":"0","infected":"15,501","daily_infected":"0","vaccines":"242,916","daily_vaccines":"0","country":"Djibouti","iso":"DJ","region":"Africa","last_update":"2022-08-27 15:25:11"},{"confirmed":"15,235","daily_confirmed":"494","recovered":"0","daily_recovered":"0","deaths":"12","daily_deaths":"0","infected":"15,223","daily_infected":"494","vaccines":"204,860","daily_vaccines":"0","country":"Tonga","iso":"TO","region":"Oceania","last_update":"2022-08-27 15:25:11"},{"confirmed":"14,931","daily_confirmed":"0","recovered":"0","daily_recovered":"0","deaths":"244","daily_deaths":"0","infected":"14,687","daily_infected":"0","vaccines":"11,707,462","daily_vaccines":"0","country":"Nicaragua","iso":"NI","region":"Americas","last_update":"2022-08-27 15:25:11"},{"confirmed":"14,862","daily_confirmed":"0","recovered":"0","daily_recovered":"0","deaths":"113","daily_deaths":"0","infected":"14,749","daily_infected":"0","vaccines":"1,395,131","daily_vaccines":"0","country":"Central African Republic","iso":"CF","region":"Africa","last_update":"2022-08-27 15:25:11"},{"confirmed":"14,852","daily_confirmed":"0","recovered":"0","daily_recovered":"0","deaths":"68","daily_deaths":"0","infected":"14,784","daily_infected":"0","vaccines":"67,431","daily_vaccines":"0","country":"Dominica","iso":"DM","region":"Americas","last_update":"2022-08-27 15:25:11"},{"confirmed":"14,506","daily_confirmed":"256","recovered":"0","daily_recovered":"0","deaths":"16","daily_deaths":"1","infected":"14,490","daily_infected":"255","vaccines":"0","daily_vaccines":"0","country":"Marshall Islands","iso":"MH","region":"Oceania","last_update":"2022-08-27 15:25:11"},{"confirmed":"14,363","daily_confirmed":"6","recovered":"0","daily_recovered":"0","deaths":"61","daily_deaths":"0","infected":"14,302","daily_infected":"6","vaccines":"65,140","daily_vaccines":"0","country":"Monaco","iso":"MC","region":"Europe","last_update":"2022-08-27 15:25:11"},{"confirmed":"12,311","daily_confirmed":"0","recovered":"0","daily_recovered":"0","deaths":"371","daily_deaths":"0","infected":"11,940","daily_infected":"0","vaccines":"815,861","daily_vaccines":"0","country":"Gambia","iso":"GM","region":"Africa","last_update":"2022-08-27 15:25:11"},{"confirmed":"11,922","daily_confirmed":"0","recovered":"0","daily_recovered":"0","deaths":"2,155","daily_deaths":"0","infected":"9,767","daily_infected":"0","vaccines":"880,609","daily_vaccines":"0","country":"Yemen","iso":"YE","region":"Asia","last_update":"2022-08-27 15:25:11"},{"confirmed":"11,784","daily_confirmed":"7","recovered":"0","daily_recovered":"0","deaths":"14","daily_deaths":"0","infected":"11,770","daily_infected":"7","vaccines":"289,912","daily_vaccines":"0","country":"Vanuatu","iso":"VU","region":"Oceania","last_update":"2022-08-27 15:25:11"},{"confirmed":"10,151","daily_confirmed":"2","recovered":"0","daily_recovered":"0","deaths":"103","daily_deaths":"0","infected":"10,048","daily_infected":"2","vaccines":"0","daily_vaccines":"0","country":"Eritrea","iso":"ER","region":"Africa","last_update":"2022-08-27 15:25:11"},{"confirmed":"9,420","daily_confirmed":"5","recovered":"0","daily_recovered":"0","deaths":"115","daily_deaths":"0","infected":"9,305","daily_infected":"5","vaccines":"72,502","daily_vaccines":"0","country":"Saint Vincent and the Grenadines","iso":"VC","region":"Americas","last_update":"2022-08-27 15:25:11"},{"confirmed":"9,263","daily_confirmed":"0","recovered":"0","daily_recovered":"0","deaths":"312","daily_deaths":"0","infected":"8,951","daily_infected":"0","vaccines":"4,532,244","daily_vaccines":"0","country":"Niger","iso":"NE","region":"Africa","last_update":"2022-08-27 15:25:11"},{"confirmed":"8,949","daily_confirmed":"0","recovered":"0","daily_recovered":"0","deaths":"145","daily_deaths":"0","infected":"8,804","daily_infected":"0","vaccines":"128,267","daily_vaccines":"0","country":"Antigua and Barbuda","iso":"AG","region":"Americas","last_update":"2022-08-27 15:25:11"},{"confirmed":"8,482","daily_confirmed":"0","recovered":"0","daily_recovered":"0","deaths":"174","daily_deaths":"0","infected":"8,308","daily_infected":"0","vaccines":"592,533","daily_vaccines":"0","country":"Guinea-Bissau","iso":"GW","region":"Africa","last_update":"2022-08-27 15:25:11"},{"confirmed":"8,445","daily_confirmed":"20","recovered":"0","daily_recovered":"0","deaths":"161","daily_deaths":"0","infected":"8,284","daily_infected":"20","vaccines":"804,403","daily_vaccines":"0","country":"Comoros","iso":"KM","region":"Africa","last_update":"2022-08-27 15:25:11"},{"confirmed":"7,744","daily_confirmed":"0","recovered":"0","daily_recovered":"0","deaths":"126","daily_deaths":"0","infected":"7,618","daily_infected":"0","vaccines":"3,493,386","daily_vaccines":"0","country":"Sierra Leone","iso":"SL","region":"Africa","last_update":"2022-08-27 15:25:11"},{"confirmed":"7,732","daily_confirmed":"0","recovered":"0","daily_recovered":"0","deaths":"294","daily_deaths":"0","infected":"7,438","daily_infected":"0","vaccines":"2,921,554","daily_vaccines":"0","country":"Liberia","iso":"LR","region":"Africa","last_update":"2022-08-27 15:25:11"},{"confirmed":"7,491","daily_confirmed":"0","recovered":"0","daily_recovered":"0","deaths":"193","daily_deaths":"0","infected":"7,298","daily_infected":"0","vaccines":"3,873,794","daily_vaccines":"0","country":"Chad","iso":"TD","region":"Africa","last_update":"2022-08-27 15:25:11"},{"confirmed":"6,508","daily_confirmed":"1","recovered":"0","daily_recovered":"0","deaths":"46","daily_deaths":"0","infected":"6,462","daily_infected":"1","vaccines":"64,225","daily_vaccines":"0","country":"Saint Kitts and Nevis","iso":"KN","region":"Americas","last_update":"2022-08-27 15:25:11"},{"confirmed":"6,136","daily_confirmed":"0","recovered":"0","daily_recovered":"0","deaths":"76","daily_deaths":"0","infected":"6,060","daily_infected":"0","vaccines":"223,558","daily_vaccines":"0","country":"Sao Tome and Principe","iso":"ST","region":"Africa","last_update":"2022-08-27 15:25:11"},{"confirmed":"5,348","daily_confirmed":"40","recovered":"0","daily_recovered":"0","deaths":"6","daily_deaths":"0","infected":"5,342","daily_infected":"40","vaccines":"0","daily_vaccines":"0","country":"Palau","iso":"PW","region":"Oceania","last_update":"2022-08-27 15:25:11"},{"confirmed":"3,430","daily_confirmed":"0","recovered":"0","daily_recovered":"0","deaths":"13","daily_deaths":"0","infected":"3,417","daily_infected":"0","vaccines":"156,812","daily_vaccines":"0","country":"Kiribati","iso":"KI","region":"Oceania","last_update":"2022-08-27 15:25:11"},{"confirmed":"29","daily_confirmed":"0","recovered":"0","daily_recovered":"0","deaths":"0","daily_deaths":"0","infected":"29","daily_infected":"0","vaccines":"0","daily_vaccines":"0","country":"Holy See","iso":"VA","region":"Europe","last_update":"2022-08-27 15:25:11"},{"confirmed":"11","daily_confirmed":"0","recovered":"0","daily_recovered":"0","deaths":"0","daily_deaths":"0","infected":"11","daily_infected":"0","vaccines":"0","daily_vaccines":"0","country":"Antarctica","iso":"AQ","region":null,"last_update":"2022-08-27 15:25:11"}]