[{"confirmed":"114,067,979","daily_confirmed":"283,244","recovered":"64,418,459","daily_recovered":"175,176","deaths":"2,530,716","daily_deaths":"5,315","infected":"47,118,804","daily_infected":"102,753","vaccines":"9,896,521","daily_vaccines":"0","country":"World","iso":"WD","region":"WD","last_update":"2021-03-01 16:30:58"},{"confirmed":"28,605,669","daily_confirmed":"51,204","recovered":"0","daily_recovered":"0","deaths":"513,091","daily_deaths":"1,097","infected":"28,092,578","daily_infected":"50,107","vaccines":"2,794,588","daily_vaccines":"0","country":"US","iso":"US","region":"Americas","last_update":"2021-03-01 16:30:58"},{"confirmed":"11,112,241","daily_confirmed":"15,510","recovered":"10,786,452","daily_recovered":"11,283","deaths":"157,157","daily_deaths":"106","infected":"168,632","daily_infected":"4,121","vaccines":"0","daily_vaccines":"0","country":"India","iso":"IN","region":"Asia","last_update":"2021-03-01 16:30:58"},{"confirmed":"10,551,259","daily_confirmed":"34,027","recovered":"9,382,316","daily_recovered":"10,868","deaths":"254,942","daily_deaths":"721","infected":"914,001","daily_infected":"22,438","vaccines":"0","daily_vaccines":"0","country":"Brazil","iso":"BR","region":"Americas","last_update":"2021-03-01 16:30:58"},{"confirmed":"4,198,400","daily_confirmed":"11,234","recovered":"3,769,025","daily_recovered":"12,217","deaths":"84,700","daily_deaths":"370","infected":"344,675","daily_infected":"-1,353","vaccines":"52,000","daily_vaccines":"0","country":"Russia","iso":"RU","region":"Europe","last_update":"2021-03-01 16:30:58"},{"confirmed":"4,188,827","daily_confirmed":"6,055","recovered":"11,643","daily_recovered":"41","deaths":"123,083","daily_deaths":"144","infected":"4,054,101","daily_infected":"5,870","vaccines":"1,004,145","daily_vaccines":"0","country":"United Kingdom","iso":"GB","region":"Europe","last_update":"2021-03-01 16:30:58"},{"confirmed":"3,747,263","daily_confirmed":"0","recovered":"261,649","daily_recovered":"0","deaths":"85,741","daily_deaths":"0","infected":"3,399,873","daily_infected":"0","vaccines":"316","daily_vaccines":"0","country":"France","iso":"FR","region":"Europe","last_update":"2021-03-01 16:30:58"},{"confirmed":"3,188,553","daily_confirmed":"0","recovered":"150,376","daily_recovered":"0","deaths":"69,142","daily_deaths":"0","infected":"2,969,035","daily_infected":"0","vaccines":"0","daily_vaccines":"0","country":"Spain","iso":"ES","region":"Europe","last_update":"2021-03-01 16:30:58"},{"confirmed":"2,925,265","daily_confirmed":"17,440","recovered":"2,405,199","daily_recovered":"6,847","deaths":"97,699","daily_deaths":"192","infected":"422,367","daily_infected":"10,401","vaccines":"38,899","daily_vaccines":"0","country":"Italy","iso":"IT","region":"Europe","last_update":"2021-03-01 16:30:58"},{"confirmed":"2,701,588","daily_confirmed":"8,424","recovered":"2,572,234","daily_recovered":"6,511","deaths":"28,569","daily_deaths":"66","infected":"100,785","daily_infected":"1,847","vaccines":"0","daily_vaccines":"0","country":"Turkey","iso":"TR","region":"Asia","last_update":"2021-03-01 16:30:58"},{"confirmed":"2,450,295","daily_confirmed":"6,118","recovered":"2,259,548","daily_recovered":"6,578","deaths":"70,152","daily_deaths":"60","infected":"120,595","daily_infected":"-520","vaccines":"181,344","daily_vaccines":"0","country":"Germany","iso":"DE","region":"Europe","last_update":"2021-03-01 16:30:58"},{"confirmed":"2,251,690","daily_confirmed":"3,555","recovered":"2,148,249","daily_recovered":"2,799","deaths":"59,766","daily_deaths":"106","infected":"43,675","daily_infected":"650","vaccines":"0","daily_vaccines":"0","country":"Colombia","iso":"CO","region":"Americas","last_update":"2021-03-01 16:30:58"},{"confirmed":"2,107,365","daily_confirmed":"3,168","recovered":"1,905,021","daily_recovered":"5,934","deaths":"51,965","daily_deaths":"19","infected":"150,379","daily_infected":"-2,785","vaccines":"32,013","daily_vaccines":"0","country":"Argentina","iso":"AR","region":"Americas","last_update":"2021-03-01 16:30:58"},{"confirmed":"2,086,938","daily_confirmed":"2,810","recovered":"1,633,900","daily_recovered":"3,898","deaths":"185,715","daily_deaths":"458","infected":"267,323","daily_infected":"-1,546","vaccines":"24,998","daily_vaccines":"0","country":"Mexico","iso":"MX","region":"Americas","last_update":"2021-03-01 16:30:58"},{"confirmed":"1,706,986","daily_confirmed":"10,101","recovered":"1,422,829","daily_recovered":"8,368","deaths":"43,769","daily_deaths":"113","infected":"240,388","daily_infected":"1,620","vaccines":"47,600","daily_vaccines":"0","country":"Poland","iso":"PL","region":"Europe","last_update":"2021-03-01 16:30:58"},{"confirmed":"1,631,169","daily_confirmed":"8,010","recovered":"1,393,125","daily_recovered":"6,591","deaths":"60,073","daily_deaths":"93","infected":"177,971","daily_infected":"1,326","vaccines":"0","daily_vaccines":"0","country":"Iran","iso":"IR","region":"Asia","last_update":"2021-03-01 16:30:58"},{"confirmed":"1,513,393","daily_confirmed":"1,168","recovered":"1,430,259","daily_recovered":"1,212","deaths":"49,993","daily_deaths":"52","infected":"33,141","daily_infected":"-96","vaccines":"0","daily_vaccines":"0","country":"South Africa","iso":"ZA","region":"Africa","last_update":"2021-03-01 16:30:58"},{"confirmed":"1,395,528","daily_confirmed":"5,958","recovered":"1,212,795","daily_recovered":"1,876","deaths":"27,404","daily_deaths":"98","infected":"155,329","daily_infected":"3,984","vaccines":"0","daily_vaccines":"0","country":"Ukraine","iso":"UA","region":"Europe","last_update":"2021-03-01 16:30:58"},{"confirmed":"1,334,634","daily_confirmed":"5,560","recovered":"1,142,703","daily_recovered":"6,649","deaths":"36,166","daily_deaths":"185","infected":"155,765","daily_infected":"-1,274","vaccines":"0","daily_vaccines":"0","country":"Indonesia","iso":"ID","region":"Asia","last_update":"2021-03-01 16:30:58"},{"confirmed":"1,323,863","daily_confirmed":"0","recovered":"1,225,995","daily_recovered":"0","deaths":"46,299","daily_deaths":"0","infected":"51,569","daily_infected":"0","vaccines":"0","daily_vaccines":"0","country":"Peru","iso":"PE","region":"Americas","last_update":"2021-03-01 16:30:58"},{"confirmed":"1,235,480","daily_confirmed":"7,885","recovered":"1,067,557","daily_recovered":"3,535","deaths":"20,339","daily_deaths":"145","infected":"147,584","daily_infected":"4,205","vaccines":"11,798","daily_vaccines":"0","country":"Czechia","iso":"CZ","region":"Europe","last_update":"2021-03-01 16:30:58"},{"confirmed":"1,103,564","daily_confirmed":"4,689","recovered":"14,416","daily_recovered":"38","deaths":"15,688","daily_deaths":"20","infected":"1,073,460","daily_infected":"4,631","vaccines":"0","daily_vaccines":"0","country":"Netherlands","iso":"NL","region":"Europe","last_update":"2021-03-01 16:30:58"},{"confirmed":"871,694","daily_confirmed":"2,347","recovered":"819,420","daily_recovered":"2,448","deaths":"21,990","daily_deaths":"29","infected":"30,284","daily_infected":"-130","vaccines":"0","daily_vaccines":"0","country":"Canada","iso":"CA","region":"Americas","last_update":"2021-03-01 16:30:58"},{"confirmed":"824,625","daily_confirmed":"3,207","recovered":"780,530","daily_recovered":"3,575","deaths":"20,572","daily_deaths":"96","infected":"23,523","daily_infected":"-464","vaccines":"8,650","daily_vaccines":"0","country":"Chile","iso":"CL","region":"Americas","last_update":"2021-03-01 16:30:58"},{"confirmed":"804,562","daily_confirmed":"718","recovered":"718,977","daily_recovered":"1,664","deaths":"16,317","daily_deaths":"41","infected":"69,268","daily_infected":"-987","vaccines":"32,749","daily_vaccines":"0","country":"Portugal","iso":"PT","region":"Europe","last_update":"2021-03-01 16:30:58"},{"confirmed":"801,994","daily_confirmed":"2,830","recovered":"740,352","daily_recovered":"1,783","deaths":"20,350","daily_deaths":"63","infected":"41,292","daily_infected":"984","vaccines":"10,289","daily_vaccines":"0","country":"Romania","iso":"RO","region":"Europe","last_update":"2021-03-01 16:30:58"},{"confirmed":"775,807","daily_confirmed":"2,472","recovered":"733,184","daily_recovered":"5,608","deaths":"5,752","daily_deaths":"20","infected":"36,871","daily_infected":"-3,156","vaccines":"997,449","daily_vaccines":"0","country":"Israel","iso":"IL","region":"Asia","last_update":"2021-03-01 16:30:58"},{"confirmed":"771,511","daily_confirmed":"2,097","recovered":"0","daily_recovered":"0","deaths":"22,077","daily_deaths":"25","infected":"749,434","daily_infected":"2,072","vaccines":"786","daily_vaccines":"0","country":"Belgium","iso":"BE","region":"Europe","last_update":"2021-03-01 16:30:58"},{"confirmed":"695,489","daily_confirmed":"3,248","recovered":"635,931","daily_recovered":"2,933","deaths":"13,406","daily_deaths":"23","infected":"46,152","daily_infected":"292","vaccines":"0","daily_vaccines":"0","country":"Iraq","iso":"IQ","region":"Asia","last_update":"2021-03-01 16:30:58"},{"confirmed":"657,309","daily_confirmed":"0","recovered":"0","daily_recovered":"0","deaths":"12,826","daily_deaths":"0","infected":"644,483","daily_infected":"0","vaccines":"1,921","daily_vaccines":"0","country":"Sweden","iso":"SE","region":"Europe","last_update":"2021-03-01 16:30:58"},{"confirmed":"581,365","daily_confirmed":"1,392","recovered":"546,371","daily_recovered":"1,094","deaths":"12,896","daily_deaths":"36","infected":"22,098","daily_infected":"262","vaccines":"0","daily_vaccines":"0","country":"Pakistan","iso":"PK","region":"Asia","last_update":"2021-03-01 16:30:58"},{"confirmed":"576,352","daily_confirmed":"2,105","recovered":"534,271","daily_recovered":"9,406","deaths":"12,318","daily_deaths":"29","infected":"29,763","daily_infected":"-7,330","vaccines":"0","daily_vaccines":"0","country":"Philippines","iso":"PH","region":"Asia","last_update":"2021-03-01 16:30:58"},{"confirmed":"554,932","daily_confirmed":"0","recovered":"317,600","daily_recovered":"0","deaths":"9,966","daily_deaths":"0","infected":"227,366","daily_infected":"0","vaccines":"0","daily_vaccines":"0","country":"Switzerland","iso":"CH","region":"Europe","last_update":"2021-03-01 16:30:58"},{"confirmed":"546,216","daily_confirmed":"385","recovered":"496,924","daily_recovered":"817","deaths":"8,408","daily_deaths":"8","infected":"40,884","daily_infected":"-440","vaccines":"0","daily_vaccines":"0","country":"Bangladesh","iso":"BD","region":"Asia","last_update":"2021-03-01 16:30:58"},{"confirmed":"483,654","daily_confirmed":"244","recovered":"469,046","daily_recovered":"239","deaths":"8,623","daily_deaths":"8","infected":"5,985","daily_infected":"-3","vaccines":"0","daily_vaccines":"0","country":"Morocco","iso":"MA","region":"Africa","last_update":"2021-03-01 16:30:58"},{"confirmed":"459,440","daily_confirmed":"2,123","recovered":"430,415","daily_recovered":"1,511","deaths":"8,561","daily_deaths":"23","infected":"20,464","daily_infected":"589","vaccines":"0","daily_vaccines":"0","country":"Austria","iso":"AT","region":"Europe","last_update":"2021-03-01 16:30:58"},{"confirmed":"459,259","daily_confirmed":"2,809","recovered":"0","daily_recovered":"0","deaths":"4,443","daily_deaths":"14","infected":"454,816","daily_infected":"2,795","vaccines":"0","daily_vaccines":"0","country":"Serbia","iso":"RS","region":"Europe","last_update":"2021-03-01 16:30:58"},{"confirmed":"432,090","daily_confirmed":"997","recovered":"409,163","daily_recovered":"1,299","deaths":"7,889","daily_deaths":"30","infected":"15,038","daily_infected":"-332","vaccines":"0","daily_vaccines":"0","country":"Japan","iso":"JP","region":"Asia","last_update":"2021-03-01 16:30:58"},{"confirmed":"428,599","daily_confirmed":"4,469","recovered":"321,128","daily_recovered":"1,437","deaths":"14,974","daily_deaths":"72","infected":"92,497","daily_infected":"2,960","vaccines":"5,110","daily_vaccines":"0","country":"Hungary","iso":"HU","region":"Europe","last_update":"2021-03-01 16:30:58"},{"confirmed":"391,524","daily_confirmed":"2,930","recovered":"381,225","daily_recovered":"1,517","deaths":"1,221","daily_deaths":"8","infected":"9,078","daily_infected":"1,405","vaccines":"0","daily_vaccines":"0","country":"United Arab Emirates","iso":"AE","region":"Asia","last_update":"2021-03-01 16:30:58"},{"confirmed":"391,090","daily_confirmed":"4,594","recovered":"348,599","daily_recovered":"2,312","deaths":"4,701","daily_deaths":"26","infected":"37,790","daily_infected":"2,256","vaccines":"0","daily_vaccines":"0","country":"Jordan","iso":"JO","region":"Asia","last_update":"2021-03-01 16:30:58"},{"confirmed":"377,383","daily_confirmed":"322","recovered":"368,305","daily_recovered":"294","deaths":"6,494","daily_deaths":"6","infected":"2,584","daily_infected":"22","vaccines":"0","daily_vaccines":"0","country":"Saudi Arabia","iso":"SA","region":"Asia","last_update":"2021-03-01 16:30:58"},{"confirmed":"375,050","daily_confirmed":"2,258","recovered":"291,590","daily_recovered":"3,085","deaths":"4,692","daily_deaths":"40","infected":"78,768","daily_infected":"-867","vaccines":"0","daily_vaccines":"0","country":"Lebanon","iso":"LB","region":"Asia","last_update":"2021-03-01 16:30:58"},{"confirmed":"340,915","daily_confirmed":"470","recovered":"326,213","daily_recovered":"722","deaths":"5,845","daily_deaths":"14","infected":"8,857","daily_infected":"-266","vaccines":"0","daily_vaccines":"0","country":"Panama","iso":"PA","region":"Americas","last_update":"2021-03-01 16:30:58"},{"confirmed":"308,083","daily_confirmed":"1,815","recovered":"255,300","daily_recovered":"0","deaths":"7,189","daily_deaths":"114","infected":"45,594","daily_infected":"1,701","vaccines":"0","daily_vaccines":"0","country":"Slovakia","iso":"SK","region":"Europe","last_update":"2021-03-01 16:30:58"},{"confirmed":"300,752","daily_confirmed":"2,437","recovered":"273,417","daily_recovered":"3,251","deaths":"1,130","daily_deaths":"9","infected":"26,205","daily_infected":"-823","vaccines":"0","daily_vaccines":"0","country":"Malaysia","iso":"MY","region":"Asia","last_update":"2021-03-01 16:30:58"},{"confirmed":"287,306","daily_confirmed":"1,347","recovered":"277,995","daily_recovered":"1,761","deaths":"1,976","daily_deaths":"10","infected":"7,335","daily_infected":"-424","vaccines":"0","daily_vaccines":"0","country":"Belarus","iso":"BY","region":"Europe","last_update":"2021-03-01 16:30:58"},{"confirmed":"286,155","daily_confirmed":"1,808","recovered":"247,898","daily_recovered":"9,081","deaths":"15,811","daily_deaths":"32","infected":"22,446","daily_infected":"-7,305","vaccines":"0","daily_vaccines":"0","country":"Ecuador","iso":"EC","region":"Americas","last_update":"2021-03-01 16:30:58"},{"confirmed":"274,143","daily_confirmed":"78","recovered":"270,407","daily_recovered":"82","deaths":"2,774","daily_deaths":"1","infected":"962","daily_infected":"-5","vaccines":"0","daily_vaccines":"0","country":"Nepal","iso":"NP","region":"Asia","last_update":"2021-03-01 16:30:58"},{"confirmed":"270,758","daily_confirmed":"248","recovered":"265,114","daily_recovered":"525","deaths":"3,510","daily_deaths":"11","infected":"2,134","daily_infected":"-288","vaccines":"0","daily_vaccines":"0","country":"Georgia","iso":"GE","region":"Asia","last_update":"2021-03-01 16:30:58"},{"confirmed":"262,715","daily_confirmed":"622","recovered":"238,982","daily_recovered":"346","deaths":"3,162","daily_deaths":"0","infected":"20,571","daily_infected":"276","vaccines":"0","daily_vaccines":"0","country":"Kazakhstan","iso":"KZ","region":"Asia","last_update":"2021-03-01 16:30:58"},{"confirmed":"249,010","daily_confirmed":"463","recovered":"193,032","daily_recovered":"479","deaths":"11,649","daily_deaths":"21","infected":"44,329","daily_infected":"-37","vaccines":"0","daily_vaccines":"0","country":"Bolivia","iso":"BO","region":"Americas","last_update":"2021-03-01 16:30:58"},{"confirmed":"247,038","daily_confirmed":"332","recovered":"205,545","daily_recovered":"408","deaths":"10,191","daily_deaths":"24","infected":"31,302","daily_infected":"-100","vaccines":"4,608","daily_vaccines":"0","country":"Bulgaria","iso":"BG","region":"Europe","last_update":"2021-03-01 16:30:58"},{"confirmed":"242,973","daily_confirmed":"356","recovered":"234,234","daily_recovered":"344","deaths":"5,526","daily_deaths":"15","infected":"3,213","daily_infected":"-3","vaccines":"7,864","daily_vaccines":"0","country":"Croatia","iso":"HR","region":"Europe","last_update":"2021-03-01 16:30:58"},{"confirmed":"239,617","daily_confirmed":"608","recovered":"191,338","daily_recovered":"1,043","deaths":"3,100","daily_deaths":"7","infected":"45,179","daily_infected":"-442","vaccines":"0","daily_vaccines":"0","country":"Dominican Republic","iso":"DO","region":"Americas","last_update":"2021-03-01 16:30:58"},{"confirmed":"234,537","daily_confirmed":"270","recovered":"228,768","daily_recovered":"117","deaths":"3,220","daily_deaths":"2","infected":"2,549","daily_infected":"151","vaccines":"0","daily_vaccines":"0","country":"Azerbaijan","iso":"AZ","region":"Asia","last_update":"2021-03-01 16:30:58"},{"confirmed":"233,277","daily_confirmed":"662","recovered":"198,006","daily_recovered":"387","deaths":"8,001","daily_deaths":"27","infected":"27,270","daily_infected":"248","vaccines":"0","daily_vaccines":"0","country":"Tunisia","iso":"TN","region":"Africa","last_update":"2021-03-01 16:30:58"},{"confirmed":"219,592","daily_confirmed":"612","recovered":"23,364","daily_recovered":"0","deaths":"4,319","daily_deaths":"6","infected":"191,909","daily_infected":"606","vaccines":"1,800","daily_vaccines":"0","country":"Ireland","iso":"IE","region":"Europe","last_update":"2021-03-01 16:30:58"},{"confirmed":"211,883","daily_confirmed":"463","recovered":"202,868","daily_recovered":"333","deaths":"2,362","daily_deaths":"3","infected":"6,653","daily_infected":"127","vaccines":"34,980","daily_vaccines":"0","country":"Denmark","iso":"DK","region":"Europe","last_update":"2021-03-01 16:30:58"},{"confirmed":"204,341","daily_confirmed":"0","recovered":"177,099","daily_recovered":"0","deaths":"2,800","daily_deaths":"0","infected":"24,442","daily_infected":"0","vaccines":"55","daily_vaccines":"0","country":"Costa Rica","iso":"CR","region":"Americas","last_update":"2021-03-01 16:30:58"},{"confirmed":"199,145","daily_confirmed":"1,802","recovered":"184,785","daily_recovered":"1,461","deaths":"3,244","daily_deaths":"10","infected":"11,116","daily_infected":"331","vaccines":"9,751","daily_vaccines":"0","country":"Lithuania","iso":"LT","region":"Europe","last_update":"2021-03-01 16:30:58"},{"confirmed":"191,100","daily_confirmed":"1,269","recovered":"93,764","daily_recovered":"0","deaths":"6,504","daily_deaths":"36","infected":"90,832","daily_infected":"1,233","vaccines":"2,339","daily_vaccines":"0","country":"Greece","iso":"GR","region":"Europe","last_update":"2021-03-01 16:30:58"},{"confirmed":"190,852","daily_confirmed":"962","recovered":"179,209","daily_recovered":"1,012","deaths":"1,083","daily_deaths":"5","infected":"10,560","daily_infected":"-55","vaccines":"2,500","daily_vaccines":"0","country":"Kuwait","iso":"KW","region":"Asia","last_update":"2021-03-01 16:30:58"},{"confirmed":"190,081","daily_confirmed":"454","recovered":"175,210","daily_recovered":"0","deaths":"3,836","daily_deaths":"0","infected":"11,035","daily_infected":"454","vaccines":"10,890","daily_vaccines":"0","country":"Slovenia","iso":"SI","region":"Europe","last_update":"2021-03-01 16:30:58"},{"confirmed":"185,453","daily_confirmed":"597","recovered":"166,178","daily_recovered":"689","deaths":"3,949","daily_deaths":"25","infected":"15,326","daily_infected":"-117","vaccines":"0","daily_vaccines":"0","country":"Moldova","iso":"MD","region":"Europe","last_update":"2021-03-01 16:30:58"},{"confirmed":"183,612","daily_confirmed":"1,703","recovered":"166,936","daily_recovered":"817","deaths":"2,042","daily_deaths":"17","infected":"14,634","daily_infected":"869","vaccines":"0","daily_vaccines":"0","country":"West Bank and Gaza","iso":"PS","region":"Asia","last_update":"2021-03-01 16:30:58"},{"confirmed":"182,424","daily_confirmed":"595","recovered":"140,892","daily_recovered":"432","deaths":"10,688","daily_deaths":"49","infected":"30,844","daily_infected":"114","vaccines":"0","daily_vaccines":"0","country":"Egypt","iso":"EG","region":"Africa","last_update":"2021-03-01 16:30:58"},{"confirmed":"174,542","daily_confirmed":"207","recovered":"161,511","daily_recovered":"382","deaths":"6,393","daily_deaths":"19","infected":"6,638","daily_infected":"-194","vaccines":"0","daily_vaccines":"0","country":"Guatemala","iso":"GT","region":"Americas","last_update":"2021-03-01 16:30:58"},{"confirmed":"172,058","daily_confirmed":"265","recovered":"163,394","daily_recovered":"85","deaths":"3,192","daily_deaths":"2","infected":"5,472","daily_infected":"178","vaccines":"0","daily_vaccines":"0","country":"Armenia","iso":"AM","region":"Asia","last_update":"2021-03-01 16:30:58"},{"confirmed":"170,304","daily_confirmed":"550","recovered":"66,513","daily_recovered":"66","deaths":"4,151","daily_deaths":"10","infected":"99,640","daily_infected":"474","vaccines":"0","daily_vaccines":"0","country":"Honduras","iso":"HN","region":"Americas","last_update":"2021-03-01 16:30:58"},{"confirmed":"163,664","daily_confirmed":"467","recovered":"153,621","daily_recovered":"402","deaths":"258","daily_deaths":"1","infected":"9,785","daily_infected":"64","vaccines":"0","daily_vaccines":"0","country":"Qatar","iso":"QA","region":"Asia","last_update":"2021-03-01 16:30:58"},{"confirmed":"159,474","daily_confirmed":"937","recovered":"133,435","daily_recovered":"990","deaths":"3,181","daily_deaths":"14","infected":"22,858","daily_infected":"-67","vaccines":"0","daily_vaccines":"0","country":"Paraguay","iso":"PY","region":"Americas","last_update":"2021-03-01 16:30:58"},{"confirmed":"159,072","daily_confirmed":"1,019","recovered":"134,858","daily_recovered":"122","deaths":"2,365","daily_deaths":"11","infected":"21,849","daily_infected":"886","vaccines":"0","daily_vaccines":"0","country":"Ethiopia","iso":"ET","region":"Africa","last_update":"2021-03-01 16:30:58"},{"confirmed":"155,657","daily_confirmed":"240","recovered":"133,768","daily_recovered":"512","deaths":"1,907","daily_deaths":"2","infected":"19,982","daily_infected":"-274","vaccines":"0","daily_vaccines":"0","country":"Nigeria","iso":"NG","region":"Africa","last_update":"2021-03-01 16:30:58"},{"confirmed":"141,896","daily_confirmed":"6","recovered":"131,480","daily_recovered":"26","deaths":"3,199","daily_deaths":"0","infected":"7,217","daily_infected":"-20","vaccines":"0","daily_vaccines":"0","country":"Burma","iso":"MM","region":"Asia","last_update":"2021-03-01 16:30:58"},{"confirmed":"141,496","daily_confirmed":"908","recovered":"132,459","daily_recovered":"775","deaths":"1,570","daily_deaths":"8","infected":"7,467","daily_infected":"125","vaccines":"6,516","daily_vaccines":"0","country":"Oman","iso":"OM","region":"Asia","last_update":"2021-03-01 16:30:58"},{"confirmed":"139,116","daily_confirmed":"377","recovered":"130,834","daily_recovered":"0","deaths":"1,344","daily_deaths":"3","infected":"6,938","daily_infected":"374","vaccines":"0","daily_vaccines":"0","country":"Venezuela","iso":"VE","region":"Americas","last_update":"2021-03-01 16:30:58"},{"confirmed":"133,338","daily_confirmed":"880","recovered":"120,240","daily_recovered":"748","deaths":"2,179","daily_deaths":"5","infected":"10,919","daily_infected":"127","vaccines":"0","daily_vaccines":"0","country":"Libya","iso":"LY","region":"Africa","last_update":"2021-03-01 16:30:58"},{"confirmed":"130,979","daily_confirmed":"0","recovered":"115,847","daily_recovered":"0","deaths":"5,071","daily_deaths":"0","infected":"10,061","daily_infected":"0","vaccines":"0","daily_vaccines":"0","country":"Bosnia and Herzegovina","iso":"BA","region":"Europe","last_update":"2021-03-01 16:30:58"},{"confirmed":"122,394","daily_confirmed":"616","recovered":"115,089","daily_recovered":"617","deaths":"449","daily_deaths":"5","infected":"6,856","daily_infected":"-6","vaccines":"58,643","daily_vaccines":"0","country":"Bahrain","iso":"BH","region":"Asia","last_update":"2021-03-01 16:30:58"},{"confirmed":"113,092","daily_confirmed":"132","recovered":"78,098","daily_recovered":"122","deaths":"2,983","daily_deaths":"4","infected":"32,011","daily_infected":"6","vaccines":"0","daily_vaccines":"0","country":"Algeria","iso":"DZ","region":"Africa","last_update":"2021-03-01 16:30:58"},{"confirmed":"107,167","daily_confirmed":"952","recovered":"69,773","daily_recovered":"804","deaths":"1,796","daily_deaths":"21","infected":"35,598","daily_infected":"127","vaccines":"0","daily_vaccines":"0","country":"Albania","iso":"AL","region":"Europe","last_update":"2021-03-01 16:30:58"},{"confirmed":"105,973","daily_confirmed":"325","recovered":"86,678","daily_recovered":"69","deaths":"1,856","daily_deaths":"2","infected":"17,439","daily_infected":"254","vaccines":"0","daily_vaccines":"0","country":"Kenya","iso":"KE","region":"Africa","last_update":"2021-03-01 16:30:58"},{"confirmed":"102,787","daily_confirmed":"305","recovered":"91,233","daily_recovered":"167","deaths":"3,137","daily_deaths":"11","infected":"8,417","daily_infected":"127","vaccines":"0","daily_vaccines":"0","country":"North Macedonia","iso":"MK","region":"Europe","last_update":"2021-03-01 16:30:58"},{"confirmed":"100,965","daily_confirmed":"41","recovered":"95,646","daily_recovered":"43","deaths":"4,835","daily_deaths":"1","infected":"484","daily_infected":"-3","vaccines":"4,500,000","daily_vaccines":"0","country":"China","iso":"CN","region":"Asia","last_update":"2021-03-01 16:30:58"},{"confirmed":"90,031","daily_confirmed":"355","recovered":"81,070","daily_recovered":"373","deaths":"1,605","daily_deaths":"2","infected":"7,356","daily_infected":"-20","vaccines":"0","daily_vaccines":"0","country":"Korea, South","iso":"KR","region":"Asia","last_update":"2021-03-01 16:30:58"},{"confirmed":"86,251","daily_confirmed":"66","recovered":"83,210","daily_recovered":"83","deaths":"1,466","daily_deaths":"3","infected":"1,575","daily_infected":"-20","vaccines":"0","daily_vaccines":"0","country":"Kyrgyzstan","iso":"KG","region":"Asia","last_update":"2021-03-01 16:30:58"},{"confirmed":"86,186","daily_confirmed":"376","recovered":"75,255","daily_recovered":"416","deaths":"1,618","daily_deaths":"4","infected":"9,313","daily_infected":"-44","vaccines":"0","daily_vaccines":"0","country":"Latvia","iso":"LV","region":"Europe","last_update":"2021-03-01 16:30:58"},{"confirmed":"84,023","daily_confirmed":"1,437","recovered":"77,972","daily_recovered":"1,399","deaths":"607","daily_deaths":"13","infected":"5,444","daily_infected":"25","vaccines":"0","daily_vaccines":"0","country":"Ghana","iso":"GH","region":"Africa","last_update":"2021-03-01 16:30:58"},{"confirmed":"83,094","daily_confirmed":"204","recovered":"78,947","daily_recovered":"574","deaths":"464","daily_deaths":"0","infected":"3,683","daily_infected":"-370","vaccines":"0","daily_vaccines":"0","country":"Sri Lanka","iso":"LK","region":"Asia","last_update":"2021-03-01 16:30:58"},{"confirmed":"79,926","daily_confirmed":"90","recovered":"78,496","daily_recovered":"123","deaths":"622","daily_deaths":"0","infected":"808","daily_infected":"-33","vaccines":"0","daily_vaccines":"0","country":"Uzbekistan","iso":"UZ","region":"Asia","last_update":"2021-03-01 16:30:58"},{"confirmed":"78,534","daily_confirmed":"332","recovered":"74,498","daily_recovered":"889","deaths":"1,091","daily_deaths":"10","infected":"2,945","daily_infected":"-567","vaccines":"0","daily_vaccines":"0","country":"Zambia","iso":"ZM","region":"Africa","last_update":"2021-03-01 16:30:58"},{"confirmed":"75,834","daily_confirmed":"502","recovered":"66,226","daily_recovered":"446","deaths":"1,003","daily_deaths":"4","infected":"8,605","daily_infected":"52","vaccines":"0","daily_vaccines":"0","country":"Montenegro","iso":"ME","region":"Europe","last_update":"2021-03-01 16:30:58"},{"confirmed":"71,006","daily_confirmed":"180","recovered":"17,998","daily_recovered":"0","deaths":"622","daily_deaths":"0","infected":"52,386","daily_infected":"180","vaccines":"2,171","daily_vaccines":"0","country":"Norway","iso":"NO","region":"Europe","last_update":"2021-03-01 16:30:58"},{"confirmed":"68,451","daily_confirmed":"0","recovered":"59,440","daily_recovered":"0","deaths":"1,592","daily_deaths":"0","infected":"7,419","daily_infected":"0","vaccines":"0","daily_vaccines":"0","country":"Kosovo","iso":"XK","region":"XK","last_update":"2021-03-01 16:30:58"},{"confirmed":"65,600","daily_confirmed":"1,201","recovered":"49,908","daily_recovered":"199","deaths":"589","daily_deaths":"5","infected":"15,103","daily_infected":"997","vaccines":"1,907","daily_vaccines":"0","country":"Estonia","iso":"EE","region":"Europe","last_update":"2021-03-01 16:30:58"},{"confirmed":"59,936","daily_confirmed":"11","recovered":"59,823","daily_recovered":"7","deaths":"29","daily_deaths":"0","infected":"84","daily_infected":"4","vaccines":"0","daily_vaccines":"0","country":"Singapore","iso":"SG","region":"Asia","last_update":"2021-03-01 16:30:58"},{"confirmed":"59,866","daily_confirmed":"0","recovered":"55,312","daily_recovered":"0","deaths":"1,854","daily_deaths":"7","infected":"2,700","daily_infected":"-7","vaccines":"0","daily_vaccines":"0","country":"El Salvador","iso":"SV","region":"Americas","last_update":"2021-03-01 16:30:58"},{"confirmed":"59,350","daily_confirmed":"578","recovered":"41,096","daily_recovered":"335","deaths":"641","daily_deaths":"11","infected":"17,613","daily_infected":"232","vaccines":"0","daily_vaccines":"0","country":"Mozambique","iso":"MZ","region":"Africa","last_update":"2021-03-01 16:30:58"},{"confirmed":"57,994","daily_confirmed":"632","recovered":"50,039","daily_recovered":"573","deaths":"608","daily_deaths":"5","infected":"7,347","daily_infected":"54","vaccines":"0","daily_vaccines":"0","country":"Uruguay","iso":"UY","region":"Americas","last_update":"2021-03-01 16:30:58"},{"confirmed":"57,672","daily_confirmed":"620","recovered":"46,000","daily_recovered":"0","deaths":"742","daily_deaths":"0","infected":"10,930","daily_infected":"620","vaccines":"1,767","daily_vaccines":"0","country":"Finland","iso":"FI","region":"Europe","last_update":"2021-03-01 16:30:58"},{"confirmed":"55,714","daily_confirmed":"7","recovered":"49,333","daily_recovered":"45","deaths":"2,443","daily_deaths":"0","infected":"3,938","daily_infected":"-38","vaccines":"0","daily_vaccines":"0","country":"Afghanistan","iso":"AF","region":"Asia","last_update":"2021-03-01 16:30:58"},{"confirmed":"55,110","daily_confirmed":"0","recovered":"51,487","daily_recovered":"0","deaths":"637","daily_deaths":"0","infected":"2,986","daily_infected":"0","vaccines":"1,200","daily_vaccines":"0","country":"Luxembourg","iso":"LU","region":"Europe","last_update":"2021-03-01 16:30:58"},{"confirmed":"49,779","daily_confirmed":"618","recovered":"45,242","daily_recovered":"676","deaths":"322","daily_deaths":"4","infected":"4,215","daily_infected":"-62","vaccines":"0","daily_vaccines":"0","country":"Cuba","iso":"CU","region":"Americas","last_update":"2021-03-01 16:30:58"},{"confirmed":"40,357","daily_confirmed":"22","recovered":"14,666","daily_recovered":"50","deaths":"334","daily_deaths":"0","infected":"25,357","daily_infected":"-28","vaccines":"0","daily_vaccines":"0","country":"Uganda","iso":"UG","region":"Africa","last_update":"2021-03-01 16:30:58"},{"confirmed":"38,845","daily_confirmed":"203","recovered":"36,261","daily_recovered":"41","deaths":"424","daily_deaths":"4","infected":"2,160","daily_infected":"158","vaccines":"0","daily_vaccines":"0","country":"Namibia","iso":"NA","region":"NA","last_update":"2021-03-01 16:30:58"},{"confirmed":"36,089","daily_confirmed":"31","recovered":"32,666","daily_recovered":"76","deaths":"1,463","daily_deaths":"0","infected":"1,960","daily_infected":"-45","vaccines":"0","daily_vaccines":"0","country":"Zimbabwe","iso":"ZW","region":"Africa","last_update":"2021-03-01 16:30:58"},{"confirmed":"35,714","daily_confirmed":"0","recovered":"32,594","daily_recovered":"0","deaths":"551","daily_deaths":"0","infected":"2,569","daily_infected":"0","vaccines":"0","daily_vaccines":"0","country":"Cameroon","iso":"CM","region":"Africa","last_update":"2021-03-01 16:30:58"},{"confirmed":"34,707","daily_confirmed":"283","recovered":"2,057","daily_recovered":"0","deaths":"231","daily_deaths":"0","infected":"32,419","daily_infected":"283","vaccines":"0","daily_vaccines":"0","country":"Cyprus","iso":"CY","region":"Asia","last_update":"2021-03-01 16:30:58"},{"confirmed":"34,520","daily_confirmed":"265","recovered":"28,894","daily_recovered":"283","deaths":"872","daily_deaths":"6","infected":"4,754","daily_infected":"-24","vaccines":"0","daily_vaccines":"0","country":"Senegal","iso":"SN","region":"Africa","last_update":"2021-03-01 16:30:58"},{"confirmed":"32,754","daily_confirmed":"123","recovered":"32,624","daily_recovered":"1,108","deaths":"192","daily_deaths":"0","infected":"-62","daily_infected":"-985","vaccines":"0","daily_vaccines":"0","country":"Cote d'Ivoire","iso":"CI","region":"Africa","last_update":"2021-03-01 16:30:58"},{"confirmed":"31,945","daily_confirmed":"147","recovered":"18,874","daily_recovered":"450","deaths":"1,044","daily_deaths":"3","infected":"12,027","daily_infected":"-306","vaccines":"0","daily_vaccines":"0","country":"Malawi","iso":"MW","region":"Africa","last_update":"2021-03-01 16:30:58"},{"confirmed":"30,347","daily_confirmed":"31","recovered":"22,907","daily_recovered":"20","deaths":"1,880","daily_deaths":"0","infected":"5,560","daily_infected":"11","vaccines":"0","daily_vaccines":"0","country":"Sudan","iso":"SD","region":"Africa","last_update":"2021-03-01 16:30:58"},{"confirmed":"28,978","daily_confirmed":"8","recovered":"22,909","daily_recovered":"6","deaths":"909","daily_deaths":"0","infected":"5,160","daily_infected":"2","vaccines":"0","daily_vaccines":"0","country":"Australia","iso":"AU","region":"Oceania","last_update":"2021-03-01 16:30:58"},{"confirmed":"28,371","daily_confirmed":"0","recovered":"23,244","daily_recovered":"0","deaths":"310","daily_deaths":"0","infected":"4,817","daily_infected":"0","vaccines":"0","daily_vaccines":"0","country":"Botswana","iso":"BW","region":"Africa","last_update":"2021-03-01 16:30:58"},{"confirmed":"26,031","daily_confirmed":"80","recovered":"25,324","daily_recovered":"196","deaths":"83","daily_deaths":"0","infected":"624","daily_infected":"-116","vaccines":"0","daily_vaccines":"0","country":"Thailand","iso":"TH","region":"Asia","last_update":"2021-03-01 16:30:58"},{"confirmed":"25,913","daily_confirmed":"121","recovered":"18,951","daily_recovered":"0","deaths":"707","daily_deaths":"0","infected":"6,255","daily_infected":"121","vaccines":"0","daily_vaccines":"0","country":"Congo (Kinshasa)","iso":"CD","region":"Africa","last_update":"2021-03-01 16:30:58"},{"confirmed":"23,263","daily_confirmed":"446","recovered":"13,410","daily_recovered":"92","deaths":"422","daily_deaths":"5","infected":"9,431","daily_infected":"349","vaccines":"0","daily_vaccines":"0","country":"Jamaica","iso":"JM","region":"Americas","last_update":"2021-03-01 16:30:58"},{"confirmed":"22,482","daily_confirmed":"263","recovered":"19,447","daily_recovered":"192","deaths":"315","daily_deaths":"2","infected":"2,720","daily_infected":"69","vaccines":"0","daily_vaccines":"0","country":"Malta","iso":"MT","region":"Europe","last_update":"2021-03-01 16:30:58"},{"confirmed":"20,807","daily_confirmed":"25","recovered":"19,322","daily_recovered":"7","deaths":"508","daily_deaths":"2","infected":"977","daily_infected":"16","vaccines":"0","daily_vaccines":"0","country":"Angola","iso":"AO","region":"Africa","last_update":"2021-03-01 16:30:58"},{"confirmed":"19,831","daily_confirmed":"0","recovered":"19,296","daily_recovered":"0","deaths":"297","daily_deaths":"0","infected":"238","daily_infected":"0","vaccines":"0","daily_vaccines":"0","country":"Madagascar","iso":"MG","region":"Africa","last_update":"2021-03-01 16:30:58"},{"confirmed":"19,793","daily_confirmed":"196","recovered":"17,249","daily_recovered":"117","deaths":"62","daily_deaths":"1","infected":"2,482","daily_infected":"78","vaccines":"0","daily_vaccines":"0","country":"Maldives","iso":"MV","region":"Asia","last_update":"2021-03-01 16:30:58"},{"confirmed":"18,850","daily_confirmed":"60","recovered":"17,313","daily_recovered":"6","deaths":"261","daily_deaths":"0","infected":"1,276","daily_infected":"54","vaccines":"0","daily_vaccines":"0","country":"Rwanda","iso":"RW","region":"Africa","last_update":"2021-03-01 16:30:58"},{"confirmed":"17,207","daily_confirmed":"11","recovered":"16,563","daily_recovered":"21","deaths":"441","daily_deaths":"1","infected":"203","daily_infected":"-11","vaccines":"0","daily_vaccines":"0","country":"Mauritania","iso":"MR","region":"Africa","last_update":"2021-03-01 16:30:58"},{"confirmed":"17,014","daily_confirmed":"12","recovered":"14,676","daily_recovered":"230","deaths":"652","daily_deaths":"2","infected":"1,686","daily_infected":"-220","vaccines":"0","daily_vaccines":"0","country":"Eswatini","iso":"SZ","region":"Africa","last_update":"2021-03-01 16:30:58"},{"confirmed":"15,992","daily_confirmed":"98","recovered":"14,897","daily_recovered":"18","deaths":"89","daily_deaths":"0","infected":"1,006","daily_infected":"80","vaccines":"0","daily_vaccines":"0","country":"Guinea","iso":"GN","region":"Africa","last_update":"2021-03-01 16:30:58"},{"confirmed":"15,588","daily_confirmed":"55","recovered":"9,801","daily_recovered":"84","deaths":"1,027","daily_deaths":"4","infected":"4,760","daily_infected":"-33","vaccines":"0","daily_vaccines":"0","country":"Syria","iso":"SY","region":"Asia","last_update":"2021-03-01 16:30:58"},{"confirmed":"15,400","daily_confirmed":"76","recovered":"14,814","daily_recovered":"30","deaths":"147","daily_deaths":"0","infected":"439","daily_infected":"46","vaccines":"0","daily_vaccines":"0","country":"Cabo Verde","iso":"CV","region":"Africa","last_update":"2021-03-01 16:30:58"},{"confirmed":"14,564","daily_confirmed":"0","recovered":"13,143","daily_recovered":"0","deaths":"83","daily_deaths":"0","infected":"1,338","daily_infected":"0","vaccines":"0","daily_vaccines":"0","country":"Gabon","iso":"GA","region":"Africa","last_update":"2021-03-01 16:30:58"},{"confirmed":"13,308","daily_confirmed":"0","recovered":"13,218","daily_recovered":"0","deaths":"90","daily_deaths":"0","infected":"0","daily_infected":"0","vaccines":"0","daily_vaccines":"0","country":"Tajikistan","iso":"TJ","region":"Asia","last_update":"2021-03-01 16:30:58"},{"confirmed":"12,430","daily_confirmed":"0","recovered":"9,712","daily_recovered":"0","deaths":"250","daily_deaths":"0","infected":"2,468","daily_infected":"0","vaccines":"0","daily_vaccines":"0","country":"Haiti","iso":"HT","region":"Americas","last_update":"2021-03-01 16:30:58"},{"confirmed":"12,293","daily_confirmed":"0","recovered":"11,836","daily_recovered":"0","deaths":"315","daily_deaths":"0","infected":"142","daily_infected":"0","vaccines":"0","daily_vaccines":"0","country":"Belize","iso":"BZ","region":"Americas","last_update":"2021-03-01 16:30:58"},{"confirmed":"11,982","daily_confirmed":"0","recovered":"11,493","daily_recovered":"0","deaths":"142","daily_deaths":"0","infected":"347","daily_infected":"0","vaccines":"0","daily_vaccines":"0","country":"Burkina Faso","iso":"BF","region":"Africa","last_update":"2021-03-01 16:30:58"},{"confirmed":"10,866","daily_confirmed":"17","recovered":"10,446","daily_recovered":"17","deaths":"110","daily_deaths":"0","infected":"310","daily_infected":"0","vaccines":"0","daily_vaccines":"0","country":"Andorra","iso":"AD","region":"Europe","last_update":"2021-03-01 16:30:58"},{"confirmed":"10,491","daily_confirmed":"0","recovered":"3,745","daily_recovered":"0","deaths":"292","daily_deaths":"0","infected":"6,454","daily_infected":"0","vaccines":"0","daily_vaccines":"0","country":"Lesotho","iso":"LS","region":"Africa","last_update":"2021-03-01 16:30:58"},{"confirmed":"8,929","daily_confirmed":"10","recovered":"8,406","daily_recovered":"7","deaths":"172","daily_deaths":"2","infected":"351","daily_infected":"1","vaccines":"0","daily_vaccines":"0","country":"Suriname","iso":"SR","region":"Americas","last_update":"2021-03-01 16:30:58"},{"confirmed":"8,820","daily_confirmed":"0","recovered":"7,019","daily_recovered":"0","deaths":"128","daily_deaths":"0","infected":"1,673","daily_infected":"0","vaccines":"0","daily_vaccines":"0","country":"Congo (Brazzaville)","iso":"CG","region":"Africa","last_update":"2021-03-01 16:30:58"},{"confirmed":"8,585","daily_confirmed":"35","recovered":"7,972","daily_recovered":"1","deaths":"195","daily_deaths":"0","infected":"418","daily_infected":"34","vaccines":"0","daily_vaccines":"0","country":"Guyana","iso":"GY","region":"Americas","last_update":"2021-03-01 16:30:58"},{"confirmed":"8,519","daily_confirmed":"0","recovered":"7,309","daily_recovered":"0","deaths":"179","daily_deaths":"0","infected":"1,031","daily_infected":"0","vaccines":"0","daily_vaccines":"0","country":"Bahamas","iso":"BS","region":"Americas","last_update":"2021-03-01 16:30:58"},{"confirmed":"8,376","daily_confirmed":"11","recovered":"6,402","daily_recovered":"0","deaths":"353","daily_deaths":"1","infected":"1,621","daily_infected":"10","vaccines":"0","daily_vaccines":"0","country":"Mali","iso":"ML","region":"Africa","last_update":"2021-03-01 16:30:58"},{"confirmed":"7,926","daily_confirmed":"155","recovered":"4,217","daily_recovered":"0","deaths":"93","daily_deaths":"0","infected":"3,616","daily_infected":"155","vaccines":"0","daily_vaccines":"0","country":"South Sudan","iso":"SS","region":"Africa","last_update":"2021-03-01 16:30:58"},{"confirmed":"7,713","daily_confirmed":"8","recovered":"7,466","daily_recovered":"8","deaths":"139","daily_deaths":"0","infected":"108","daily_infected":"0","vaccines":"0","daily_vaccines":"0","country":"Trinidad and Tobago","iso":"TT","region":"Americas","last_update":"2021-03-01 16:30:58"},{"confirmed":"7,257","daily_confirmed":"266","recovered":"3,808","daily_recovered":"21","deaths":"239","daily_deaths":"8","infected":"3,210","daily_infected":"237","vaccines":"0","daily_vaccines":"0","country":"Somalia","iso":"SO","region":"Africa","last_update":"2021-03-01 16:30:58"},{"confirmed":"6,901","daily_confirmed":"50","recovered":"5,660","daily_recovered":"61","deaths":"84","daily_deaths":"1","infected":"1,157","daily_infected":"-12","vaccines":"0","daily_vaccines":"0","country":"Togo","iso":"TG","region":"Africa","last_update":"2021-03-01 16:30:58"},{"confirmed":"6,445","daily_confirmed":"0","recovered":"4,225","daily_recovered":"0","deaths":"173","daily_deaths":"0","infected":"2,047","daily_infected":"0","vaccines":"0","daily_vaccines":"0","country":"Nicaragua","iso":"NI","region":"Americas","last_update":"2021-03-01 16:30:58"},{"confirmed":"6,066","daily_confirmed":"1","recovered":"5,897","daily_recovered":"2","deaths":"63","daily_deaths":"0","infected":"106","daily_infected":"-1","vaccines":"0","daily_vaccines":"0","country":"Djibouti","iso":"DJ","region":"Africa","last_update":"2021-03-01 16:30:58"},{"confirmed":"6,049","daily_confirmed":"0","recovered":"6,006","daily_recovered":"0","deaths":"29","daily_deaths":"0","infected":"14","daily_infected":"0","vaccines":"4,875","daily_vaccines":"0","country":"Iceland","iso":"IS","region":"Europe","last_update":"2021-03-01 16:30:58"},{"confirmed":"6,005","daily_confirmed":"0","recovered":"5,622","daily_recovered":"0","deaths":"91","daily_deaths":"0","infected":"292","daily_infected":"0","vaccines":"0","daily_vaccines":"0","country":"Equatorial Guinea","iso":"GQ","region":"Africa","last_update":"2021-03-01 16:30:58"},{"confirmed":"5,434","daily_confirmed":"0","recovered":"4,248","daily_recovered":"0","deaths":"70","daily_deaths":"0","infected":"1,116","daily_infected":"0","vaccines":"0","daily_vaccines":"0","country":"Benin","iso":"BJ","region":"Africa","last_update":"2021-03-01 16:30:58"},{"confirmed":"5,004","daily_confirmed":"0","recovered":"4,920","daily_recovered":"0","deaths":"63","daily_deaths":"0","infected":"21","daily_infected":"0","vaccines":"0","daily_vaccines":"0","country":"Central African Republic","iso":"CF","region":"Africa","last_update":"2021-03-01 16:30:58"},{"confirmed":"4,740","daily_confirmed":"0","recovered":"4,250","daily_recovered":"0","deaths":"172","daily_deaths":"0","infected":"318","daily_infected":"0","vaccines":"0","daily_vaccines":"0","country":"Niger","iso":"NE","region":"Africa","last_update":"2021-03-01 16:30:58"},{"confirmed":"4,712","daily_confirmed":"21","recovered":"4,089","daily_recovered":"0","deaths":"150","daily_deaths":"2","infected":"473","daily_infected":"19","vaccines":"0","daily_vaccines":"0","country":"Gambia","iso":"GM","region":"Africa","last_update":"2021-03-01 16:30:58"},{"confirmed":"3,973","daily_confirmed":"0","recovered":"3,475","daily_recovered":"0","deaths":"140","daily_deaths":"0","infected":"358","daily_infected":"0","vaccines":"0","daily_vaccines":"0","country":"Chad","iso":"TD","region":"Africa","last_update":"2021-03-01 16:30:58"},{"confirmed":"3,887","daily_confirmed":"0","recovered":"2,621","daily_recovered":"0","deaths":"79","daily_deaths":"0","infected":"1,187","daily_infected":"0","vaccines":"0","daily_vaccines":"0","country":"Sierra Leone","iso":"SL","region":"Africa","last_update":"2021-03-01 16:30:58"},{"confirmed":"3,716","daily_confirmed":"0","recovered":"3,257","daily_recovered":"0","deaths":"74","daily_deaths":"0","infected":"385","daily_infected":"0","vaccines":"0","daily_vaccines":"0","country":"San Marino","iso":"SM","region":"Europe","last_update":"2021-03-01 16:30:58"},{"confirmed":"3,571","daily_confirmed":"0","recovered":"3,314","daily_recovered":"10","deaths":"144","daily_deaths":"0","infected":"113","daily_infected":"-10","vaccines":"0","daily_vaccines":"0","country":"Comoros","iso":"KM","region":"Africa","last_update":"2021-03-01 16:30:58"},{"confirmed":"3,390","daily_confirmed":"34","recovered":"3,013","daily_recovered":"101","deaths":"35","daily_deaths":"0","infected":"342","daily_infected":"-67","vaccines":"0","daily_vaccines":"0","country":"Saint Lucia","iso":"LC","region":"Americas","last_update":"2021-03-01 16:30:58"},{"confirmed":"3,262","daily_confirmed":"15","recovered":"2,613","daily_recovered":"12","deaths":"48","daily_deaths":"0","infected":"601","daily_infected":"3","vaccines":"0","daily_vaccines":"0","country":"Guinea-Bissau","iso":"GW","region":"Africa","last_update":"2021-03-01 16:30:58"},{"confirmed":"3,068","daily_confirmed":"30","recovered":"2,407","daily_recovered":"63","deaths":"33","daily_deaths":"0","infected":"628","daily_infected":"-33","vaccines":"0","daily_vaccines":"0","country":"Barbados","iso":"BB","region":"Americas","last_update":"2021-03-01 16:30:58"},{"confirmed":"2,952","daily_confirmed":"45","recovered":"2,299","daily_recovered":"116","deaths":"2","daily_deaths":"0","infected":"651","daily_infected":"-71","vaccines":"0","daily_vaccines":"0","country":"Mongolia","iso":"MN","region":"Asia","last_update":"2021-03-01 16:30:58"},{"confirmed":"2,847","daily_confirmed":"0","recovered":"2,253","daily_recovered":"0","deaths":"7","daily_deaths":"0","infected":"587","daily_infected":"0","vaccines":"0","daily_vaccines":"0","country":"Eritrea","iso":"ER","region":"Africa","last_update":"2021-03-01 16:30:58"},{"confirmed":"2,618","daily_confirmed":"26","recovered":"2,287","daily_recovered":"24","deaths":"11","daily_deaths":"0","infected":"320","daily_infected":"2","vaccines":"0","daily_vaccines":"0","country":"Seychelles","iso":"SC","region":"Africa","last_update":"2021-03-01 16:30:58"},{"confirmed":"2,567","daily_confirmed":"1","recovered":"2,484","daily_recovered":"0","deaths":"54","daily_deaths":"0","infected":"29","daily_infected":"1","vaccines":"0","daily_vaccines":"0","country":"Liechtenstein","iso":"LI","region":"Europe","last_update":"2021-03-01 16:30:58"},{"confirmed":"2,448","daily_confirmed":"16","recovered":"1,876","daily_recovered":"32","deaths":"35","daily_deaths":"0","infected":"537","daily_infected":"-16","vaccines":"0","daily_vaccines":"0","country":"Vietnam","iso":"VN","region":"Asia","last_update":"2021-03-01 16:30:58"},{"confirmed":"2,378","daily_confirmed":"2","recovered":"2,285","daily_recovered":"0","deaths":"26","daily_deaths":"0","infected":"67","daily_infected":"2","vaccines":"0","daily_vaccines":"0","country":"New Zealand","iso":"NZ","region":"Oceania","last_update":"2021-03-01 16:30:58"},{"confirmed":"2,285","daily_confirmed":"16","recovered":"1,435","daily_recovered":"0","deaths":"634","daily_deaths":"3","infected":"216","daily_infected":"13","vaccines":"0","daily_vaccines":"0","country":"Yemen","iso":"YE","region":"Asia","last_update":"2021-03-01 16:30:58"},{"confirmed":"2,209","daily_confirmed":"28","recovered":"773","daily_recovered":"0","deaths":"3","daily_deaths":"0","infected":"1,433","daily_infected":"28","vaccines":"0","daily_vaccines":"0","country":"Burundi","iso":"BI","region":"Africa","last_update":"2021-03-01 16:30:58"},{"confirmed":"2,014","daily_confirmed":"4","recovered":"1,884","daily_recovered":"0","deaths":"85","daily_deaths":"0","infected":"45","daily_infected":"4","vaccines":"0","daily_vaccines":"0","country":"Liberia","iso":"LR","region":"Africa","last_update":"2021-03-01 16:30:58"},{"confirmed":"1,956","daily_confirmed":"3","recovered":"1,710","daily_recovered":"6","deaths":"24","daily_deaths":"0","infected":"222","daily_infected":"-3","vaccines":"0","daily_vaccines":"0","country":"Monaco","iso":"MC","region":"Europe","last_update":"2021-03-01 16:30:58"},{"confirmed":"1,786","daily_confirmed":"0","recovered":"1,382","daily_recovered":"27","deaths":"29","daily_deaths":"1","infected":"375","daily_infected":"-28","vaccines":"0","daily_vaccines":"0","country":"Sao Tome and Principe","iso":"ST","region":"Africa","last_update":"2021-03-01 16:30:58"},{"confirmed":"1,556","daily_confirmed":"0","recovered":"932","daily_recovered":"0","deaths":"8","daily_deaths":"0","infected":"616","daily_infected":"0","vaccines":"0","daily_vaccines":"0","country":"Saint Vincent and the Grenadines","iso":"VC","region":"Americas","last_update":"2021-03-01 16:30:58"},{"confirmed":"1,275","daily_confirmed":"0","recovered":"846","daily_recovered":"0","deaths":"12","daily_deaths":"0","infected":"417","daily_infected":"0","vaccines":"0","daily_vaccines":"0","country":"Papua New Guinea","iso":"PG","region":"Oceania","last_update":"2021-03-01 16:30:58"},{"confirmed":"955","daily_confirmed":"1","recovered":"919","daily_recovered":"2","deaths":"9","daily_deaths":"0","infected":"27","daily_infected":"-1","vaccines":"0","daily_vaccines":"0","country":"Taiwan*","iso":"TW","region":"Asia","last_update":"2021-03-01 16:30:58"},{"confirmed":"867","daily_confirmed":"0","recovered":"865","daily_recovered":"3","deaths":"1","daily_deaths":"0","infected":"1","daily_infected":"-3","vaccines":"0","daily_vaccines":"0","country":"Bhutan","iso":"BT","region":"Asia","last_update":"2021-03-01 16:30:58"},{"confirmed":"820","daily_confirmed":"15","recovered":"477","daily_recovered":"0","deaths":"0","daily_deaths":"0","infected":"343","daily_infected":"15","vaccines":"0","daily_vaccines":"0","country":"Cambodia","iso":"KH","region":"Asia","last_update":"2021-03-01 16:30:58"},{"confirmed":"730","daily_confirmed":"4","recovered":"301","daily_recovered":"10","deaths":"14","daily_deaths":"0","infected":"415","daily_infected":"-6","vaccines":"0","daily_vaccines":"0","country":"Antigua and Barbuda","iso":"AG","region":"Americas","last_update":"2021-03-01 16:30:58"},{"confirmed":"610","daily_confirmed":"0","recovered":"571","daily_recovered":"0","deaths":"10","daily_deaths":"0","infected":"29","daily_infected":"0","vaccines":"0","daily_vaccines":"0","country":"Mauritius","iso":"MU","region":"Africa","last_update":"2021-03-01 16:30:58"},{"confirmed":"509","daily_confirmed":"0","recovered":"183","daily_recovered":"0","deaths":"21","daily_deaths":"0","infected":"305","daily_infected":"0","vaccines":"0","daily_vaccines":"0","country":"Tanzania","iso":"TZ","region":"Africa","last_update":"2021-03-01 16:30:58"},{"confirmed":"186","daily_confirmed":"0","recovered":"181","daily_recovered":"0","deaths":"3","daily_deaths":"0","infected":"2","daily_infected":"0","vaccines":"0","daily_vaccines":"0","country":"Brunei","iso":"BN","region":"Asia","last_update":"2021-03-01 16:30:58"},{"confirmed":"148","daily_confirmed":"0","recovered":"147","daily_recovered":"0","deaths":"1","daily_deaths":"0","infected":"0","daily_infected":"0","vaccines":"0","daily_vaccines":"0","country":"Grenada","iso":"GD","region":"Americas","last_update":"2021-03-01 16:30:58"},{"confirmed":"142","daily_confirmed":"0","recovered":"127","daily_recovered":"0","deaths":"0","daily_deaths":"0","infected":"15","daily_infected":"0","vaccines":"0","daily_vaccines":"0","country":"Dominica","iso":"DM","region":"Americas","last_update":"2021-03-01 16:30:58"},{"confirmed":"113","daily_confirmed":"2","recovered":"90","daily_recovered":"1","deaths":"0","daily_deaths":"0","infected":"23","daily_infected":"1","vaccines":"0","daily_vaccines":"0","country":"Timor-Leste","iso":"TL","region":"Asia","last_update":"2021-03-01 16:30:58"},{"confirmed":"59","daily_confirmed":"0","recovered":"54","daily_recovered":"0","deaths":"2","daily_deaths":"0","infected":"3","daily_infected":"0","vaccines":"0","daily_vaccines":"0","country":"Fiji","iso":"FJ","region":"Oceania","last_update":"2021-03-01 16:30:58"},{"confirmed":"45","daily_confirmed":"0","recovered":"42","daily_recovered":"0","deaths":"0","daily_deaths":"0","infected":"3","daily_infected":"0","vaccines":"0","daily_vaccines":"0","country":"Laos","iso":"LA","region":"Asia","last_update":"2021-03-01 16:30:58"},{"confirmed":"41","daily_confirmed":"0","recovered":"40","daily_recovered":"0","deaths":"0","daily_deaths":"0","infected":"1","daily_infected":"0","vaccines":"0","daily_vaccines":"0","country":"Saint Kitts and Nevis","iso":"KN","region":"Americas","last_update":"2021-03-01 16:30:58"},{"confirmed":"27","daily_confirmed":"0","recovered":"15","daily_recovered":"0","deaths":"0","daily_deaths":"0","infected":"12","daily_infected":"0","vaccines":"0","daily_vaccines":"0","country":"Holy See","iso":"VA","region":"Europe","last_update":"2021-03-01 16:30:58"},{"confirmed":"18","daily_confirmed":"0","recovered":"14","daily_recovered":"0","deaths":"0","daily_deaths":"0","infected":"4","daily_infected":"0","vaccines":"0","daily_vaccines":"0","country":"Solomon Islands","iso":"SB","region":"Oceania","last_update":"2021-03-01 16:30:58"},{"confirmed":"4","daily_confirmed":"0","recovered":"4","daily_recovered":"0","deaths":"0","daily_deaths":"0","infected":"0","daily_infected":"0","vaccines":"0","daily_vaccines":"0","country":"Marshall Islands","iso":"MH","region":"Oceania","last_update":"2021-03-01 16:30:58"},{"confirmed":"3","daily_confirmed":"0","recovered":"2","daily_recovered":"0","deaths":"0","daily_deaths":"0","infected":"1","daily_infected":"0","vaccines":"0","daily_vaccines":"0","country":"Samoa","iso":"WS","region":"Oceania","last_update":"2021-03-01 16:30:58"},{"confirmed":"1","daily_confirmed":"0","recovered":"1","daily_recovered":"0","deaths":"0","daily_deaths":"0","infected":"0","daily_infected":"0","vaccines":"0","daily_vaccines":"0","country":"Vanuatu","iso":"VU","region":"Oceania","last_update":"2021-03-01 16:30:58"}]